{"Version": "1.0.0", "LINES": [{"text": "three that's five", "start": 90.9, "duration": 5.46, "ents": [{"label_": "CARDINAL", "text": "three"}, {"label_": "CARDINAL", "text": "five"}], "sentiment": 0.0}, {"text": "five", "start": 96.36, "duration": 2.18, "ents": [{"label_": "CARDINAL", "text": "five"}], "sentiment": 0.0}, {"text": "three numbers in their correct position", "start": 141.72, "duration": 3.48, "ents": [{"label_": "CARDINAL", "text": "three"}], "sentiment": 0.0}, {"text": "to add up unless the two are connected", "start": 161.4, "duration": 5.64, "ents": [{"label_": "CARDINAL", "text": "two"}], "sentiment": 0.0}, {"text": "truly in a downswing first we have to", "start": 183.48, "duration": 5.28, "ents": [{"label_": "ORDINAL", "text": "first"}], "sentiment": 0.25}, {"text": "second somewhat academic definition of", "start": 211.2, "duration": 4.259, "ents": [{"label_": "ORDINAL", "text": "second"}], "sentiment": 0.0}, {"text": "test up schneidered the first modern", "start": 218.519, "duration": 4.5, "ents": [{"label_": "ORDINAL", "text": "first"}], "sentiment": 0.225}, {"text": "French psychologist Alfred binay in 1904", "start": 223.019, "duration": 5.821, "ents": [{"label_": "NORP", "text": "French"}, {"label_": "PERSON", "text": "Alfred binay"}, {"label_": "DATE", "text": "1904"}], "sentiment": 0.0}, {"text": "the first world war the U.S military", "start": 252.12, "duration": 4.739, "ents": [{"label_": "GPE", "text": "U.S"}], "sentiment": 0.075}, {"text": "one criticism centers on the", "start": 388.28, "duration": 4.56, "ents": [], "sentiment": 0.0}, {"text": "an IQ score of 130 or higher is", "start": 449.4, "duration": 6.12, "ents": [{"label_": "CARDINAL", "text": "130"}], "sentiment": 0.25}, {"text": "considered highly gifted below 70 is", "start": 452.52, "duration": 5.7, "ents": [{"label_": "DATE", "text": "70"}], "sentiment": 0.5}, {"text": "extremes account for two percent of the", "start": 458.22, "duration": 4.28, "ents": [{"label_": "PERCENT", "text": "two percent"}], "sentiment": 0.0}, {"text": "in 1984 he concluded that humans are", "start": 482.58, "duration": 4.26, "ents": [{"label_": "DATE", "text": "1984"}], "sentiment": 0.0}, {"text": "observed that starting after 1930 IQ", "start": 489.5, "duration": 4.78, "ents": [{"label_": "DATE", "text": "1930"}], "sentiment": 0.0}, {"text": "scores increased by about four points", "start": 492.539, "duration": 3.901, "ents": [{"label_": "CARDINAL", "text": "about four"}], "sentiment": 0.0}, {"text": "every 10 years that's described as the", "start": 494.28, "duration": 3.74, "ents": [{"label_": "DATE", "text": "10 years"}], "sentiment": 0.0}, {"text": "from 1984 would have been considered", "start": 503.819, "duration": 6.44, "ents": [{"label_": "DATE", "text": "1984"}], "sentiment": 0.0}, {"text": "highly gifted around 1900.", "start": 506.4, "duration": 6.019, "ents": [{"label_": "DATE", "text": "1900"}], "sentiment": 0.5}, {"text": "why did it rise in the first place", "start": 510.259, "duration": 4.84, "ents": [{"label_": "ORDINAL", "text": "first"}], "sentiment": 0.25}, {"text": "last thousand or ten thousand years", "start": 516.779, "duration": 3.62, "ents": [{"label_": "DATE", "text": "last thousand or ten thousand years"}], "sentiment": 0.0}, {"text": "evolved like this in the last 60 years", "start": 533.279, "duration": 4.281, "ents": [{"label_": "DATE", "text": "the last 60 years"}], "sentiment": 0.0}, {"text": "in the early 20th century nearly half", "start": 557.399, "duration": 4.861, "ents": [{"label_": "DATE", "text": "the early 20th century"}], "sentiment": -0.022222222222222216}, {"text": "over the course of the 20th century our", "start": 590.399, "duration": 4.741, "ents": [{"label_": "DATE", "text": "the 20th century"}], "sentiment": 0.0}, {"text": "everyday environments became one that", "start": 593.1, "duration": 3.72, "ents": [], "sentiment": -0.2}, {"text": "but in 2004 Norwegian researchers", "start": 645.12, "duration": 5.52, "ents": [{"label_": "DATE", "text": "2004"}, {"label_": "NORP", "text": "Norwegian"}], "sentiment": 0.0}, {"text": "in 2016 German psychologist Hina", "start": 672.0, "duration": 5.22, "ents": [{"label_": "DATE", "text": "2016"}, {"label_": "NORP", "text": "German"}, {"label_": "PERSON", "text": "Hina"}], "sentiment": 0.0}, {"text": "if students write on my exam that 80 of", "start": 704.18, "duration": 5.98, "ents": [{"label_": "CARDINAL", "text": "80"}], "sentiment": 0.0}, {"text": "intelligence is hereditary and 20 is", "start": 707.519, "duration": 5.76, "ents": [{"label_": "CARDINAL", "text": "20"}], "sentiment": 0.0}, {"text": "in 2018 a Norwegian study showed that", "start": 734.519, "duration": 5.701, "ents": [{"label_": "DATE", "text": "2018"}, {"label_": "NORP", "text": "Norwegian"}], "sentiment": 0.0}, {"text": "increased 300 fold since the 1970s", "start": 782.399, "duration": 9.481, "ents": [{"label_": "CARDINAL", "text": "300"}, {"label_": "DATE", "text": "the 1970s"}], "sentiment": 0.0}, {"text": "that humans can process about 11 to 60", "start": 900.779, "duration": 5.18, "ents": [{"label_": "CARDINAL", "text": "about 11 to 60"}], "sentiment": 0.0}, {"text": "bits per second", "start": 903.12, "duration": 2.839, "ents": [{"label_": "ORDINAL", "text": "second"}], "sentiment": 0.0}, {"text": "but 11 million bits are flooding our", "start": 906.74, "duration": 7.26, "ents": [{"label_": "CARDINAL", "text": "11 million"}], "sentiment": 0.0}, {"text": "brains every second", "start": 910.92, "duration": 3.08, "ents": [{"label_": "ORDINAL", "text": "second"}], "sentiment": 0.0}, {"text": "convincing one was done at Stanford with", "start": 964.8, "duration": 3.96, "ents": [{"label_": "ORG", "text": "Stanford"}], "sentiment": 0.5}, {"text": "500 students were divided into three", "start": 971.899, "duration": 4.961, "ents": [{"label_": "CARDINAL", "text": "500"}, {"label_": "CARDINAL", "text": "three"}], "sentiment": 0.0}, {"text": "first tether smartphones taken away the", "start": 976.86, "duration": 4.44, "ents": [{"label_": "ORDINAL", "text": "first"}], "sentiment": 0.25}, {"text": "second were simply told to turn them off", "start": 979.38, "duration": 4.139, "ents": [{"label_": "ORDINAL", "text": "second"}], "sentiment": 0.0}, {"text": "and the third were allowed to have them", "start": 981.3, "duration": 3.24, "ents": [{"label_": "ORDINAL", "text": "third"}], "sentiment": 0.0}, {"text": "the third group performed the worst and", "start": 984.54, "duration": 4.2, "ents": [{"label_": "ORDINAL", "text": "third"}], "sentiment": -0.5}, {"text": "trying to Outsource certain tasks first", "start": 1017.72, "duration": 4.5, "ents": [{"label_": "ORG", "text": "Outsource"}, {"label_": "ORDINAL", "text": "first"}], "sentiment": 0.23214285714285715}, {"text": "that one stimulus triggers another that", "start": 1071.44, "duration": 5.38, "ents": [{"label_": "CARDINAL", "text": "one"}], "sentiment": 0.0}, {"text": "okay so we lose a point or two on an IQ", "start": 1081.52, "duration": 5.86, "ents": [{"label_": "CARDINAL", "text": "two"}], "sentiment": 0.5}, {"text": "would have to read six books with not a", "start": 1171.02, "duration": 4.14, "ents": [{"label_": "CARDINAL", "text": "six"}], "sentiment": 0.0}, {"text": "right by the seventh grade everyone has", "start": 1207.08, "duration": 6.86, "ents": [{"label_": "ORDINAL", "text": "seventh"}], "sentiment": 0.2857142857142857}, {"text": "two minutes I think the average", "start": 1236.299, "duration": 4.201, "ents": [{"label_": "TIME", "text": "two minutes"}], "sentiment": -0.15}, {"text": "listening time on Spotify is one and a", "start": 1238.22, "duration": 4.8, "ents": [{"label_": "GPE", "text": "Spotify"}], "sentiment": 0.0}, {"text": "something simple 10 minutes and easily", "start": 1303.74, "duration": 4.98, "ents": [{"label_": "TIME", "text": "10 minutes"}], "sentiment": 0.21666666666666667}, {"text": "an alarm for five minutes and then try", "start": 1308.72, "duration": 3.36, "ents": [{"label_": "TIME", "text": "five minutes"}], "sentiment": 0.0}, {"text": "calves tense after five minutes the", "start": 1334.46, "duration": 4.26, "ents": [{"label_": "TIME", "text": "five minutes"}], "sentiment": -0.3333333333333333}, {"text": "and it's not just among vegans about one", "start": 1392.44, "duration": 6.04, "ents": [{"label_": "CARDINAL", "text": "about one"}], "sentiment": 0.0}, {"text": "out of three European adults does not", "start": 1396.26, "duration": 4.68, "ents": [{"label_": "CARDINAL", "text": "three"}, {"label_": "NORP", "text": "European"}], "sentiment": 0.0}, {"text": "one question remains why is this", "start": 1472.7, "duration": 4.979, "ents": [{"label_": "CARDINAL", "text": "one"}], "sentiment": 0.0}, {"text": "than all humans a 68 year old child", "start": 1482.179, "duration": 5.041, "ents": [{"label_": "DATE", "text": "68 year old"}], "sentiment": 0.1}, {"text": "sometimes even five numbers can be too", "start": 1503.539, "duration": 3.841, "ents": [{"label_": "CARDINAL", "text": "five"}], "sentiment": 0.0}], "VIDEO_ID": "s8TM_RD3qrI", "VIDEO_DATA": [{"videoId": "s8TM_RD3qrI", "channelId": "UCW39zufHfsuGgpLviKh297Q", "description": "For a long time, mankind was getting smarter and smarter. In fact, our progress seemed unstoppable. Intelligence research ...", "title": "Are we getting dumber and dumber? | DW Documentary", "publishedAt": "2023-01-15T17:00:24Z"}]}