{"Version": "1.0.0", "LINES": [{"text": "than I thought so in March of 2020 was", "start": 35.76, "duration": 5.7, "ents": [{"label_": "DATE", "text": "March of 2020"}], "sentiment": 0.0}, {"text": "masks so people are missing out on one", "start": 51.84, "duration": 5.28, "ents": [{"label_": "CARDINAL", "text": "one"}], "sentiment": -0.2}, {"text": "might be missing one of the biggest", "start": 74.22, "duration": 3.899, "ents": [], "sentiment": -0.2}, {"text": "they're the first generation I think to", "start": 129.3, "duration": 4.439, "ents": [{"label_": "ORDINAL", "text": "first"}], "sentiment": 0.25}, {"text": "Boomers for the first generation to be", "start": 142.86, "duration": 4.379, "ents": [{"label_": "ORDINAL", "text": "first"}], "sentiment": 0.25}, {"text": "so in 2000 it crashed but did they fix", "start": 223.879, "duration": 6.661, "ents": [{"label_": "DATE", "text": "2000"}], "sentiment": 0.0}, {"text": "at 2008 it crashed again did they fix", "start": 230.54, "duration": 7.02, "ents": [{"label_": "DATE", "text": "2008"}], "sentiment": 0.0}, {"text": "said it was already in Picard 2016. it", "start": 327.9, "duration": 6.18, "ents": [{"label_": "DATE", "text": "2016"}], "sentiment": 0.0}, {"text": "people fish and there's 20 percent of", "start": 352.979, "duration": 3.901, "ents": [{"label_": "PERCENT", "text": "20 percent"}], "sentiment": 0.0}, {"text": "the population 80 20 year olds called", "start": 355.32, "duration": 6.48, "ents": [{"label_": "DATE", "text": "80 20 year olds"}], "sentiment": 0.0}, {"text": "prado's law 80 versus 20 so 80 of the", "start": 356.88, "duration": 8.4, "ents": [{"label_": "CARDINAL", "text": "80"}, {"label_": "CARDINAL", "text": "20"}], "sentiment": 0.0}, {"text": "people need to learn how to fish twenty", "start": 361.8, "duration": 5.76, "ents": [{"label_": "CARDINAL", "text": "twenty"}], "sentiment": 0.0}, {"text": "1971. and instead of fixing the problem", "start": 403.46, "duration": 6.519, "ents": [{"label_": "DATE", "text": "1971"}], "sentiment": 0.0}, {"text": "trillion is and why I'm saying the FED", "start": 412.5, "duration": 5.16, "ents": [{"label_": "ORG", "text": "FED"}], "sentiment": 0.0}, {"text": "is incompetent and dying so a trillion", "start": 414.72, "duration": 5.64, "ents": [], "sentiment": -0.35}, {"text": "just hit a button say one trillion to a", "start": 423.3, "duration": 5.459, "ents": [{"label_": "CARDINAL", "text": "one trillion"}], "sentiment": 0.0}, {"text": "trillion so if you spent a dollar every", "start": 425.52, "duration": 6.36, "ents": [], "sentiment": -0.1}, {"text": "second it would take you 35", "start": 428.759, "duration": 7.56, "ents": [{"label_": "ORDINAL", "text": "second"}, {"label_": "CARDINAL", "text": "35"}], "sentiment": 0.0}, {"text": "000 years to spend a trillion dollars I", "start": 431.88, "duration": 6.06, "ents": [{"label_": "DATE", "text": "000 years"}, {"label_": "MONEY", "text": "a trillion dollars"}], "sentiment": 0.0}, {"text": "you and I are going to be around 35", "start": 437.94, "duration": 5.159, "ents": [], "sentiment": 0.0}, {"text": "000 years but I think they just printed", "start": 440.4, "duration": 4.68, "ents": [{"label_": "DATE", "text": "000 years"}], "sentiment": 0.0}, {"text": "three or four trillion dollars in the", "start": 443.099, "duration": 3.54, "ents": [{"label_": "QUANTITY", "text": "three or four trillion dollars"}], "sentiment": 0.0}, {"text": "when I was a kid I got 15 percent on my", "start": 467.46, "duration": 5.579, "ents": [{"label_": "PERCENT", "text": "15 percent"}], "sentiment": 0.0}, {"text": "science to figure that one out you know", "start": 491.4, "duration": 4.68, "ents": [], "sentiment": 0.0}, {"text": "guys pay 40 in taxes remember money is", "start": 581.16, "duration": 4.619, "ents": [{"label_": "CARDINAL", "text": "40"}], "sentiment": 0.0}, {"text": "pay 40 taxes they work for money they", "start": 585.779, "duration": 5.221, "ents": [{"label_": "CARDINAL", "text": "40"}], "sentiment": 0.0}, {"text": "pay 60 taxes so the small entrepreneurs", "start": 587.94, "duration": 4.56, "ents": [{"label_": "CARDINAL", "text": "60"}], "sentiment": -0.25}, {"text": "20 tax we're inside investors I put my", "start": 600.12, "duration": 5.94, "ents": [{"label_": "CARDINAL", "text": "20"}], "sentiment": 0.0}], "VIDEO_ID": "yemwCAba9eY", "VIDEO_DATA": [{"videoId": "yemwCAba9eY", "channelId": "UCN-qfPKTQ_Wxr8vZLVfM95w", "description": "Robert Kiyosaki warns about the biggest stock market crash in world history. He explains how to prepare for this crisis, outlines the ...", "title": "&quot;The Biggest Stock Market Crash Is On Us NOW!&quot; - Robert Kiyosaki&#39;s Last WARNING", "publishedAt": "2022-09-16T19:21:22Z"}]}