{"Version": "1.0.0", "LINES": [{"text": "Two or three days ago Joy came and\ntold us that they killed her twins.", "start": 287.36, "duration": 3.84, "ents": [{"label_": "DATE", "text": "Two or three days ago"}, {"label_": "PERSON", "text": "Joy"}], "sentiment": 0.30000000000000004}, {"text": "She was here three\nor four years ago?", "start": 298.56, "duration": 2.08, "ents": [{"label_": "CARDINAL", "text": "three"}, {"label_": "DATE", "text": "four years ago"}], "sentiment": 0.0}, {"text": "Five years, and then the traffickers\nkilled her twins in Nigeria.", "start": 303.8, "duration": 5.08, "ents": [{"label_": "DATE", "text": "Five years"}, {"label_": "GPE", "text": "Nigeria"}], "sentiment": -0.2}, {"text": "We need to use our own\ncase number, not that old one.", "start": 430.44, "duration": 2.76, "ents": [], "sentiment": 0.35}, {"text": "We immediately set up a wiretap\nthat involved two individuals.", "start": 518.72, "duration": 3.92, "ents": [{"label_": "CARDINAL", "text": "two"}], "sentiment": 0.0}, {"text": "One individual was the\nwoman who contacted her.", "start": 522.88, "duration": 2.92, "ents": [{"label_": "CARDINAL", "text": "One"}], "sentiment": 0.0}, {"text": "Joy had to pay 20,000\ndollars to get out of debt", "start": 537.44, "duration": 3.44, "ents": [{"label_": "MONEY", "text": "20,000\ndollars"}], "sentiment": 0.8}, {"text": "So after I got to Italy, one day I\nwent to work, my stomach was hurting.", "start": 616.96, "duration": 6.8, "ents": [{"label_": "GPE", "text": "Italy"}, {"label_": "DATE", "text": "one day"}], "sentiment": 0.0}, {"text": "I was on Facebook one\nday, I just saw my friend.", "start": 683.6, "duration": 3.0, "ents": [{"label_": "DATE", "text": "one\nday"}], "sentiment": 0.0}, {"text": "One day, I just said to my friend,", "start": 713.88, "duration": 3.6, "ents": [{"label_": "DATE", "text": "One day"}], "sentiment": 0.0}, {"text": "We\u2019ve already undertaken\nthree big investigations", "start": 870.36, "duration": 2.92, "ents": [{"label_": "CARDINAL", "text": "three"}], "sentiment": 0.0}, {"text": "31 to 33,000 euros for a kilo of\ncocaine or 38,000 for heroin.", "start": 935.32, "duration": 5.52, "ents": [{"label_": "CARDINAL", "text": "31"}, {"label_": "CARDINAL", "text": "33,000"}, {"label_": "CARDINAL", "text": "38,000"}], "sentiment": 0.0}, {"text": "I was twelve years old.", "start": 967.04, "duration": 1.68, "ents": [{"label_": "DATE", "text": "twelve years old"}], "sentiment": 0.1}, {"text": "We were eating from\none hand to one hand.", "start": 974.36, "duration": 3.08, "ents": [], "sentiment": 0.0}, {"text": "I stayed in the church for four years,\nbut believe me, it was still tough.", "start": 1004.28, "duration": 5.24, "ents": [{"label_": "DATE", "text": "four years"}], "sentiment": -0.3888888888888889}, {"text": "That was how I got pregnant\nfor the first time in my life.", "start": 1035.16, "duration": 3.36, "ents": [{"label_": "ORDINAL", "text": "first"}], "sentiment": 0.29166666666666663}, {"text": "I had the first child\nand the second child.", "start": 1041.4, "duration": 2.76, "ents": [{"label_": "ORDINAL", "text": "first"}, {"label_": "ORDINAL", "text": "second"}], "sentiment": 0.125}, {"text": "In the second relationship\nthe man was from Edo State.", "start": 1052.04, "duration": 3.88, "ents": [{"label_": "ORDINAL", "text": "second"}, {"label_": "GPE", "text": "Edo State"}], "sentiment": 0.0}, {"text": "So one day a rich woman who\nwas in Italy before as a madam,", "start": 1075.4, "duration": 4.52, "ents": [{"label_": "DATE", "text": "one day"}, {"label_": "GPE", "text": "Italy"}], "sentiment": 0.375}, {"text": "When you get there, you\npay me 40,000 US dollars", "start": 1087.84, "duration": 3.48, "ents": [{"label_": "MONEY", "text": "40,000 US dollars"}], "sentiment": 0.0}, {"text": "and after six months,\nyou will finish the payment", "start": 1091.32, "duration": 3.52, "ents": [{"label_": "DATE", "text": "six months"}], "sentiment": 0.0}, {"text": "So when it was about\nsix months, God told me,", "start": 1144.2, "duration": 3.4, "ents": [{"label_": "DATE", "text": "six months"}], "sentiment": 0.0}, {"text": "Within the six months,\nwith other girls,", "start": 1156.92, "duration": 2.28, "ents": [{"label_": "DATE", "text": "the six months"}], "sentiment": -0.125}, {"text": "even in the next ten years\npeople will still be trafficked.", "start": 1216.48, "duration": 5.44, "ents": [{"label_": "DATE", "text": "the next ten years"}], "sentiment": 0.0}, {"text": "Girls who come by boat pay\nbetween 25 and 35 thousand euros.", "start": 1324.44, "duration": 4.4, "ents": [{"label_": "DATE", "text": "between 25 and"}, {"label_": "CARDINAL", "text": "35 thousand"}], "sentiment": 0.0}, {"text": "I think coming by plane costs\nbetween 50 and 60 thousand euros.", "start": 1328.84, "duration": 4.48, "ents": [{"label_": "DATE", "text": "between 50 and 60 thousand"}], "sentiment": 0.0}, {"text": "Some were flown to\nGreece first and from there", "start": 1358.2, "duration": 3.44, "ents": [{"label_": "PERSON", "text": "Greece"}, {"label_": "ORDINAL", "text": "first"}], "sentiment": 0.25}, {"text": "Just to give you an idea, I think two\nor three of the passports are fake.", "start": 1388.12, "duration": 4.2, "ents": [{"label_": "CARDINAL", "text": "two"}, {"label_": "CARDINAL", "text": "three"}], "sentiment": -0.5}, {"text": "One is from France\nand one is from Belgium.", "start": 1409.0, "duration": 2.72, "ents": [{"label_": "CARDINAL", "text": "One"}, {"label_": "GPE", "text": "France"}, {"label_": "CARDINAL", "text": "one"}, {"label_": "GPE", "text": "Belgium"}], "sentiment": 0.0}, {"text": "they ended up with average\ndebs of over 55,000 euros", "start": 1415.44, "duration": 3.44, "ents": [{"label_": "CARDINAL", "text": "over 55,000"}], "sentiment": -0.15}, {"text": "They worked off the debt over\nthe course of 15 months or so.", "start": 1420.6, "duration": 3.76, "ents": [{"label_": "DATE", "text": "15 months or so"}], "sentiment": 0.0}, {"text": "That was the first time I went because\nI needed to do it to come to Europe.", "start": 1454.24, "duration": 4.76, "ents": [{"label_": "ORDINAL", "text": "first"}, {"label_": "LOC", "text": "Europe"}], "sentiment": 0.25}, {"text": "It was the first time.\nThey brought me to a little room,", "start": 1459.0, "duration": 3.88, "ents": [{"label_": "ORDINAL", "text": "first"}], "sentiment": 0.03125}, {"text": "He was the one asking me to\nrepeat everything that he said.", "start": 1474.6, "duration": 3.72, "ents": [], "sentiment": 0.0}, {"text": "because I am one of those that\nwrites stories of the girls in Italy", "start": 1710.28, "duration": 3.56, "ents": [{"label_": "GPE", "text": "Italy"}], "sentiment": 0.0}, {"text": "and stayed for two or three days.", "start": 1841.08, "duration": 2.8, "ents": [{"label_": "DATE", "text": "two or three days"}], "sentiment": 0.0}, {"text": "and found 110,000 euros\nplus the debt register.", "start": 1887.76, "duration": 3.84, "ents": [{"label_": "CARDINAL", "text": "110,000"}], "sentiment": 0.0}, {"text": "It logs debts of 330,000 euros\nowed by various girls.", "start": 1898.96, "duration": 4.44, "ents": [{"label_": "CARDINAL", "text": "330,000"}], "sentiment": 0.0}, {"text": "This trial is one of the\nthree big investigations", "start": 1969.36, "duration": 2.84, "ents": [{"label_": "CARDINAL", "text": "three"}], "sentiment": 0.0}, {"text": "2.5 million.", "start": 2332.52, "duration": 2.08, "ents": [{"label_": "CARDINAL", "text": "2.5 million"}], "sentiment": 0.0}, {"text": "about from 210 euros to\n420 euros for each woman.", "start": 2344.72, "duration": 5.68, "ents": [{"label_": "CARDINAL", "text": "210"}, {"label_": "CARDINAL", "text": "420"}], "sentiment": 0.0}, {"text": "One idea is that she would\nhave taken all the cash with her.", "start": 2522.24, "duration": 3.08, "ents": [{"label_": "CARDINAL", "text": "One"}], "sentiment": 0.0}, {"text": "from the Hawala bankers, no\none will be able to trace back", "start": 2556.36, "duration": 3.92, "ents": [{"label_": "ORG", "text": "Hawala"}], "sentiment": 0.25}, {"text": "Right, and I\u2019m sure no one\nwill ever be able to trace that.", "start": 2567.52, "duration": 3.52, "ents": [], "sentiment": 0.42857142857142855}, {"text": "One of Victory\u2019s sisters.\nWhat\u2019s your name?", "start": 2764.68, "duration": 4.16, "ents": [{"label_": "CARDINAL", "text": "One"}], "sentiment": 0.0}, {"text": "I don\u2019t have money\nto start one up.", "start": 2868.68, "duration": 2.88, "ents": [{"label_": "CARDINAL", "text": "one"}], "sentiment": 0.0}, {"text": "and they give me my\ndocuments for five years.", "start": 2956.56, "duration": 2.88, "ents": [{"label_": "DATE", "text": "five years"}], "sentiment": 0.0}, {"text": "In those 1999, it took me like eight\nmonths to be able to speak to someone.", "start": 3046.12, "duration": 4.96, "ents": [{"label_": "DATE", "text": "1999"}, {"label_": "DATE", "text": "like eight\nmonths"}], "sentiment": 0.5}], "VIDEO_ID": "UaCutB_Hy7M", "VIDEO_DATA": [{"videoId": "UaCutB_Hy7M", "channelId": "UCW39zufHfsuGgpLviKh297Q", "description": "Criminal networks from Nigeria earn billions trading drugs and trafficking humans. They lure young women to Europe, where ...", "title": "Nigerian trafficking networks | DW Documentary", "publishedAt": "2023-04-29T16:00:27Z"}]}