{"Version": "1.0.0", "LINES": [{"text": "DEMANDS INCREASE FROM THE SECOND", "start": 2.002, "duration": 5.372, "ents": [{"label_": "ORDINAL", "text": "SECOND"}], "sentiment": 0.0}, {"text": "BELOW $80 IN", "start": 140.707, "duration": 3.103, "ents": [{"label_": "MONEY", "text": "80"}], "sentiment": 0.0}, {"text": "80 HAS CERTAINLY BEEN A FLOOR.", "start": 160.927, "duration": 2.869, "ents": [{"label_": "CARDINAL", "text": "80"}], "sentiment": 0.21428571428571427}, {"text": ">> CHEVRON HIT A RECORD IN 2022,", "start": 196.696, "duration": 5.172, "ents": [{"label_": "DATE", "text": "2022"}], "sentiment": 0.0}, {"text": "'23.", "start": 204.237, "duration": 1.535, "ents": [{"label_": "DATE", "text": "'23"}], "sentiment": 0.0}], "VIDEO_ID": "NcXFj7IApI4", "VIDEO_DATA": [{"videoId": "XWnWStrUPgA", "channelId": "UCrp_UI8XtuYfpiqluWLD7Lw", "description": "CNBC's Carl Quintanilla reports on Goldman Sachs and Morgan Stanley's quarterly earnings results.", "title": "Goldman misses EPS and revenue estimates; Morgan Stanley beats revenue and EPS estimates", "publishedAt": "2023-01-17T13:33:06Z", "phrases": [], "source": "CNBC television", "has_report": true, "video_path": "/ytube/CNBC television/2023/XWnWStrUPgA"}, {"videoId": "NcXFj7IApI4", "channelId": "UCrp_UI8XtuYfpiqluWLD7Lw", "description": "Chevron CEO Mike Worth joins 'Squawk Box' to discuss the rest of the winter's global energy picture, oil prices, and more.", "title": "Chevron CEO: Europe will make it through this winter in reasonably good shape", "publishedAt": "2023-01-17T13:33:11Z"}, {"videoId": "BLdfyDv8Nkk", "channelId": "UCrp_UI8XtuYfpiqluWLD7Lw", "description": "S&P Global vice chairman Dan Yergin discusses the impact of China's reopening on energy prices, and the effect interest rates ...", "title": "Yergin: China&#39;s economic rebound could play a big factor in the oil market this year", "publishedAt": "2023-01-17T12:56:57Z"}, {"videoId": "8Sc1GfEUZJA", "channelId": "UCrp_UI8XtuYfpiqluWLD7Lw", "description": "Brian Sullivan's daily RBI segment discusses Bank of America's top stock picks for the year.", "title": "Brian Sullivan&#39;s RBI: Bank of America&#39;s One Pick Per Sector Stock List", "publishedAt": "2023-01-17T12:02:10Z"}, {"videoId": "K6QM-hhnh5A", "channelId": "UCrp_UI8XtuYfpiqluWLD7Lw", "description": "Live from Davos, Bain Capital Co-Chairman Stephen Pagliuca discusses the firm's investment outlook.", "title": "Bain Capital Co-Chairman Stephen Pagliuca on investing in the future", "publishedAt": "2023-01-17T11:58:01Z"}]}