{"Version": "1.0.0", "LINES": [{"text": "WE ARE JUST PAST 100 DAYS SINCE ", "start": 116.866, "duration": 3.867, "ents": [], "sentiment": -0.25}, {"text": "BOOKS FROM 1864. ", "start": 176.816, "duration": 5.317, "ents": [{"label_": "DATE", "text": "1864"}], "sentiment": 0.0}, {"text": "LET ME SAY THAT AGAIN, 1864. ", "start": 181.133, "duration": 2.667, "ents": [{"label_": "DATE", "text": "1864"}], "sentiment": 0.0}, {"text": "THAT IS OVER 150 YEARS AGO. ", "start": 182.366, "duration": 5.534, "ents": [{"label_": "DATE", "text": "150 YEARS AGO"}], "sentiment": 0.0}, {"text": "NEARLY 50 YEARS AGO AND THAT ", "start": 190.2, "duration": 6.883, "ents": [], "sentiment": 0.1}, {"text": "CONGRESS, THE FIRST PIECE OF ", "start": 214.466, "duration": 7.7, "ents": [{"label_": "ORG", "text": "CONGRESS"}, {"label_": "ORDINAL", "text": "FIRST"}], "sentiment": 0.25}, {"text": "THE 50th ANNIVERSARY OF ROE V. ", "start": 232.05, "duration": 4.933, "ents": [{"label_": "PRODUCT", "text": "ROE V."}], "sentiment": 0.0}, {"text": ">> TWO TOPICS, IS THE ", "start": 248.866, "duration": 7.634, "ents": [{"label_": "CARDINAL", "text": "TWO"}, {"label_": "ORG", "text": "TOPICS"}], "sentiment": 0.0}, {"text": "GAS PRICES HAVE FALLEN BY $1.15 ", "start": 295.366, "duration": 2.217, "ents": [{"label_": "MONEY", "text": "1.15"}], "sentiment": 0.0}, {"text": "FASTEST IN OVER ONE DECADE. ", "start": 303.283, "duration": 1.9, "ents": [{"label_": "DATE", "text": "ONE DECADE"}], "sentiment": 0.0}, {"text": "DRIVER FAMILY SAVES ABOUT $120 ", "start": 305.283, "duration": 3.867, "ents": [{"label_": "PERSON", "text": "DRIVER FAMILY SAVES"}, {"label_": "MONEY", "text": "ABOUT $120"}], "sentiment": 0.0}, {"text": "FIVE CENTS, AND STATES THAT ", "start": 328.0, "duration": 5.65, "ents": [{"label_": "MONEY", "text": "FIVE CENTS"}], "sentiment": 0.0}, {"text": "THAN $.30 AND WISCONSIN IS DOWN ", "start": 338.45, "duration": 5.866, "ents": [], "sentiment": -0.15555555555555559}, {"text": "$.20. ", "start": 344.216, "duration": 1.5, "ents": [], "sentiment": 0.0}, {"text": "OREGON IS DOWN $.20 THIS WEEK ", "start": 344.416, "duration": 7.25, "ents": [], "sentiment": -0.15555555555555559}, {"text": "AT MICHIGAN IS DOWN BY $.16 ", "start": 345.816, "duration": 14.517, "ents": [{"label_": "ORG", "text": "MICHIGAN"}], "sentiment": -0.15555555555555559}, {"text": "THIS WEEK, OHIO, 13 CENTS DOWN. ", "start": 351.766, "duration": 9.767, "ents": [{"label_": "DATE", "text": "THIS WEEK"}, {"label_": "GPE", "text": "OHIO"}, {"label_": "MONEY", "text": "13 CENTS"}], "sentiment": -0.15555555555555559}, {"text": "$12 BILLION IN THE CR? ", "start": 403.55, "duration": 2.233, "ents": [{"label_": "MONEY", "text": "$12 BILLION"}], "sentiment": 0.0}, {"text": "THE APPROACH, THE FIRST BILL, ", "start": 532.383, "duration": 7.333, "ents": [{"label_": "ORG", "text": "APPROACH"}, {"label_": "ORDINAL", "text": "FIRST"}], "sentiment": 0.25}, {"text": "50th ANNERSA OF ROE V. ", "start": 547.183, "duration": 1.15, "ents": [{"label_": "ORDINAL", "text": "50th"}, {"label_": "PRODUCT", "text": "ROE V."}], "sentiment": 0.0}, {"text": "50 YEARS. ", "start": 573.75, "duration": 1.3, "ents": [{"label_": "DATE", "text": "50 YEARS"}], "sentiment": 0.0}, {"text": ">> TWO DIFFERENT TOPICS. HE ", "start": 594.5, "duration": 7.783, "ents": [{"label_": "CARDINAL", "text": "TWO"}], "sentiment": 0.0}, {"text": "AND THIS ONE, THE MAJORITY OF ", "start": 646.316, "duration": 3.817, "ents": [], "sentiment": 0.0}, {"text": "DELIRED A $.5 BILLION IN ", "start": 680.85, "duration": 3.416, "ents": [{"label_": "MONEY", "text": "$.5 BILLION"}], "sentiment": 0.0}, {"text": ">> JUST ONE QUESTION. ", "start": 838.85, "duration": 2.066, "ents": [{"label_": "CARDINAL", "text": "ONE"}], "sentiment": 0.0}, {"text": "WHAT IF NOVEMBER 8 DOES NOT GO ", "start": 845.75, "duration": 5.516, "ents": [{"label_": "DATE", "text": "NOVEMBER 8"}], "sentiment": 0.0}, {"text": "REMEMBER, THIS IS ALMOST 50 ", "start": 949.8, "duration": 4.733, "ents": [], "sentiment": 0.0}, {"text": "THE LAST 3 TO 4 MONTHS? ", "start": 967.65, "duration": 2.266, "ents": [{"label_": "DATE", "text": "LAST 3 TO 4"}], "sentiment": 0.0}, {"text": "FIRST BILL, A BILL TO CODIFY ", "start": 1062.1, "duration": 7.116, "ents": [], "sentiment": 0.25}, {"text": ">> SAY THAT ONE MORE TIME. ", "start": 1082.733, "duration": 2.467, "ents": [{"label_": "CARDINAL", "text": "ONE"}, {"label_": "ORG", "text": "TIME"}], "sentiment": 0.5}, {"text": "WHAT WILL BE THE FIRST BILL ", "start": 1093.366, "duration": 2.067, "ents": [{"label_": "ORDINAL", "text": "FIRST"}], "sentiment": 0.25}, {"text": "AND THAT THEY BELIEVE, FOR 50 ", "start": 1132.783, "duration": 7.167, "ents": [{"label_": "CARDINAL", "text": "50"}], "sentiment": 0.0}, {"text": "YEARS, NEARLY 50 YEARS, THE ", "start": 1138.15, "duration": 3.033, "ents": [{"label_": "DATE", "text": "YEARS"}], "sentiment": 0.1}, {"text": "50th ANNIVERSARY, LAYING OUT ", "start": 1160.566, "duration": 1.934, "ents": [], "sentiment": 0.0}, {"text": "THAT HIS FIRST PIECE OF ", "start": 1161.266, "duration": 6.484, "ents": [{"label_": "ORDINAL", "text": "FIRST"}], "sentiment": 0.25}, {"text": ">> ONE MORE ON THE SPR RELEASE, ", "start": 1206.75, "duration": 2.233, "ents": [{"label_": "CARDINAL", "text": "ONE"}], "sentiment": 0.5}, {"text": "MAYBE IT 80 MILLION BARRELS, ", "start": 1220.466, "duration": 8.3, "ents": [{"label_": "CARDINAL", "text": "80 MILLION"}], "sentiment": 0.0}, {"text": "FASTEST PACE IN OVER ONE DECADE ", "start": 1273.016, "duration": 3.5, "ents": [{"label_": "DATE", "text": "ONE DECADE"}], "sentiment": 0.0}, {"text": ">> IT HAS BEEN EIGHT MONTHS ", "start": 1342.35, "duration": 2.2, "ents": [], "sentiment": 0.0}, {"text": "TURNED 32-YEAR-OLD TODAY. ", "start": 1347.95, "duration": 6.45, "ents": [{"label_": "DATE", "text": "32-YEAR-OLD"}], "sentiment": 0.0}, {"text": "FIGHTING SO HARD. MY FIRST ", "start": 1354.5, "duration": 6.633, "ents": [], "sentiment": -0.020833333333333343}, {"text": "IS HIS NUMBER ONE ECONOMIC ", "start": 1549.8, "duration": 1.166, "ents": [{"label_": "CARDINAL", "text": "ONE"}], "sentiment": 0.2}, {"text": ">> IT IS HIS NUMBER ONE ", "start": 1553.9, "duration": 1.566, "ents": [{"label_": "CARDINAL", "text": "ONE"}], "sentiment": 0.0}, {"text": "BUT, NEXT YEAR, HIS FIRST BILL ", "start": 1558.2, "duration": 3.6, "ents": [{"label_": "ORG", "text": "NEXT YEAR"}, {"label_": "ORDINAL", "text": "FIRST"}], "sentiment": 0.125}, {"text": "HIS NUMBER ONE DOMESTIC ", "start": 1563.9, "duration": 4.883, "ents": [{"label_": "CARDINAL", "text": "ONE"}], "sentiment": 0.0}, {"text": "PRESIDENT HAS DONE THE LAST 18 ", "start": 1571.25, "duration": 1.333, "ents": [{"label_": "DATE", "text": "LAST 18"}], "sentiment": 0.0}, {"text": "TO CREATE MORE THAN 10 MILLION ", "start": 1585.366, "duration": 2.834, "ents": [], "sentiment": 0.5}, {"text": "30 MILLION PEOPLE ARE GOING TO ", "start": 1625.433, "duration": 3.333, "ents": [{"label_": "CARDINAL", "text": "30 MILLION"}], "sentiment": 0.0}, {"text": "THE ECONOMY FOR 19 MONTHS, NOW ", "start": 1638.883, "duration": 2.0, "ents": [{"label_": "DATE", "text": "19 MONTHS"}, {"label_": "ORG", "text": "NOW"}], "sentiment": 0.0}, {"text": "BLOOMBERG IS FORECASTING A 100% ", "start": 1640.05, "duration": 1.4, "ents": [{"label_": "ORG", "text": "BLOOMBERG IS FORECASTING A"}, {"label_": "PERCENT", "text": "100%"}], "sentiment": 0.0}, {"text": "MEANS THAT WE LEAVE NO ONE ", "start": 1708.116, "duration": 1.4, "ents": [], "sentiment": 0.0}, {"text": "MORE THAN 9000 APPROVED ", "start": 1745.583, "duration": 2.733, "ents": [{"label_": "CARDINAL", "text": "9000"}], "sentiment": 0.5}, {"text": "BIDEN'S FIRST YEAR THAT UNDER ", "start": 1762.466, "duration": 4.717, "ents": [{"label_": "ORG", "text": "BIDEN'S FIRST YEAR THAT"}], "sentiment": 0.25}, {"text": "FIRST YEAR. ", "start": 1767.283, "duration": 1.3, "ents": [{"label_": "ORG", "text": "FIRST YEAR"}], "sentiment": 0.25}, {"text": "30 OUNCE OF IT, THE UNITED ", "start": 1798.433, "duration": 3.45, "ents": [{"label_": "CARDINAL", "text": "30"}, {"label_": "ORG", "text": "UNITED"}], "sentiment": 0.0}, {"text": ">> I HAVE TWO QUESTIONS, ONE ", "start": 1868.55, "duration": 7.7, "ents": [{"label_": "CARDINAL", "text": "TWO"}, {"label_": "CARDINAL", "text": "ONE"}], "sentiment": 0.0}, {"text": "DOMESTIC, ONE FOR. ", "start": 1873.75, "duration": 5.033, "ents": [{"label_": "CARDINAL", "text": "ONE"}], "sentiment": 0.0}, {"text": ">> MORE THAN ONE THIRD OF ", "start": 1909.383, "duration": 5.5, "ents": [], "sentiment": 0.25}, {"text": "OF 2020. ", "start": 1936.516, "duration": 6.067, "ents": [{"label_": "DATE", "text": "2020"}], "sentiment": 0.0}, {"text": "AND THE LEGITIMACY OF 2020. ", "start": 1936.783, "duration": 6.767, "ents": [{"label_": "DATE", "text": "2020"}], "sentiment": 0.0}, {"text": "BEEN DONE FOR THE LAST EIGHT ", "start": 2074.516, "duration": 3.167, "ents": [], "sentiment": 0.0}, {"text": ">> FOLLOWING UP, ONE OF THE ", "start": 2146.516, "duration": 4.317, "ents": [{"label_": "CARDINAL", "text": "ONE"}], "sentiment": 0.0}, {"text": "IN OCTOBER OF 2010. ", "start": 2376.816, "duration": 1.934, "ents": [{"label_": "DATE", "text": "OCTOBER OF 2010"}], "sentiment": 0.0}, {"text": "1st, THERE WILL BE MORE TRAVEL ", "start": 2386.7, "duration": 2.533, "ents": [], "sentiment": 0.5}, {"text": "NUMBER ONE, WILL THAT SIMPLY ", "start": 2457.066, "duration": 3.667, "ents": [], "sentiment": 0.0}, {"text": "NUMBER TWO ARE THERE ANY ", "start": 2467.75, "duration": 7.933, "ents": [{"label_": "CARDINAL", "text": "TWO"}], "sentiment": 0.0}, {"text": "50 YEARS AND HE BELIEVES IN THE ", "start": 2487.3, "duration": 2.533, "ents": [{"label_": "DATE", "text": "50 YEARS"}], "sentiment": 0.0}, {"text": "FIRST OF ALL, THERE ARE INDIVID ", "start": 2498.033, "duration": 10.25, "ents": [{"label_": "ORG", "text": "INDIVID"}], "sentiment": 0.25}, {"text": "CLOSED DOORS TWO WEEKS AGO, ", "start": 2554.5, "duration": 1.9, "ents": [{"label_": "DATE", "text": "TWO WEEKS AGO"}], "sentiment": -0.1}, {"text": "TH IS A TWO WEEKS AGO ", "start": 2582.633, "duration": 2.167, "ents": [{"label_": "ORG", "text": "TH"}, {"label_": "CARDINAL", "text": "TWO"}], "sentiment": 0.0}, {"text": ">> FOLLOWING UP, THE FIRST ", "start": 2624.6, "duration": 4.166, "ents": [{"label_": "ORDINAL", "text": "FIRST"}], "sentiment": 0.125}, {"text": "MAJORITY ON JANUARY 3rd OF NEXT ", "start": 2636.883, "duration": 5.433, "ents": [{"label_": "DATE", "text": "JANUARY 3rd OF NEXT"}], "sentiment": 0.0}, {"text": "DECISION, WHEN ROE WAS FIRST ", "start": 2685.8, "duration": 6.833, "ents": [{"label_": "ORDINAL", "text": "FIRST"}], "sentiment": 0.25}, {"text": "WE ARE TALKING ABOUT ALMOST 40 ", "start": 2754.066, "duration": 2.267, "ents": [], "sentiment": 0.0}, {"text": "MILLION PEOPLE WHO ARE GOING TO ", "start": 2755.3, "duration": 2.066, "ents": [], "sentiment": 0.0}, {"text": "POLICY, 23 MILLION PEOPLE ARE ", "start": 2758.8, "duration": 2.366, "ents": [{"label_": "CARDINAL", "text": "23 MILLION"}], "sentiment": 0.0}, {"text": "WE ARE TALKING ABOUT 90% OF THE ", "start": 2764.3, "duration": 4.95, "ents": [{"label_": "PERCENT", "text": "ABOUT 90%"}], "sentiment": 0.0}, {"text": "ARE MAKING UNDER $75,000, HE IS ", "start": 2775.783, "duration": 2.267, "ents": [{"label_": "MONEY", "text": "75,000"}], "sentiment": 0.0}, {"text": "AGAIN, 90% OF THEM ARE MAKING ", "start": 2800.583, "duration": 3.7, "ents": [{"label_": "PERCENT", "text": "90%"}], "sentiment": 0.0}, {"text": "LESS THAN $75,000, THEY NEED A ", "start": 2803.25, "duration": 3.466, "ents": [{"label_": "MONEY", "text": "75,000"}], "sentiment": -0.16666666666666666}], "VIDEO_ID": "pXRbD5IK19I", "VIDEO_DATA": [{"videoId": "ZsZ8Vd_4sXA", "channelId": "UCEAZeUIeJs0IjQiqTCdVSIg", "description": "stocks #stockmarket #yahoofinance Yahoo Finance Live's Brad Smith breaks down how stocks are trading after the opening bell.", "title": "Stocks edge lower in early trading, Netflix stock soars", "publishedAt": "2022-10-19T14:04:57Z", "phrases": [], "source": "Yahoo Finance", "has_report": true, "video_path": "/ytube/Yahoo Finance/2022/ZsZ8Vd_4sXA"}, {"videoId": "IMFzYJ5_pUQ", "channelId": "UCEAZeUIeJs0IjQiqTCdVSIg", "description": "Netflix #Netflixearnings #yahoofinance This segment originally aired on October 18, 2022. Manhattan Venture Partners Head of ...", "title": "Netflix&#39;s earnings beat and subscriber growth show &#39;everything is working&#39;: Analyst", "publishedAt": "2022-10-19T13:35:36Z", "phrases": [], "source": "Yahoo Finance", "has_report": true, "video_path": "/ytube/Yahoo Finance/2022/IMFzYJ5_pUQ"}, {"videoId": "mkgaSxUYah4", "channelId": "UCEAZeUIeJs0IjQiqTCdVSIg", "description": "LIVE: White House Press Secretary Karine Jean-Pierre holds briefing Don't Miss: Valley of Hype: The Culture That Built Elizabeth ...", "title": "LIVE: White House Press Secretary Karine Jean-Pierre holds briefing", "publishedAt": "2022-10-19T13:22:03Z", "phrases": [], "source": "Yahoo Finance", "has_report": false}, {"videoId": "KRyNORtBT8I", "channelId": "UCEAZeUIeJs0IjQiqTCdVSIg", "description": "Don't Miss: Valley of Hype: The Culture That Built Elizabeth Holmes WATCH HERE: https://youtu.be/Sb179GLPNYE Subscribe to ...", "title": "LIVE: President Biden delivers remarks on releasing oil from the strategic petroleum reserve", "publishedAt": "2022-10-19T13:02:52Z", "phrases": [], "source": "Yahoo Finance", "has_report": false}, {"videoId": "dKsqebuCW3g", "channelId": "UCEAZeUIeJs0IjQiqTCdVSIg", "description": "paramount #paramountCEO #yahoofinance Paramount CEO Bob Bakish speaks to Yahoo Finance's Alexandra Canal at Yahoo ...", "title": "Paramount CEO on Paramount+ growth, streaming success and why he\u2019s still bullish on theaters", "publishedAt": "2022-10-19T03:18:07Z", "phrases": [], "source": "Yahoo Finance", "has_report": true, "video_path": "/ytube/Yahoo Finance/2022/dKsqebuCW3g"}, {"videoId": "mHZGU7PwZTc", "channelId": "UCEAZeUIeJs0IjQiqTCdVSIg", "description": "ModernaCEO #COVID19vaccine #yahoofinance Moderna CEO Stephane Bancel speaks with Anjalee Khemlani at Yahoo ...", "title": "Moderna CEO on COVID vaccines: Not everyone will need an annual COVID-19 booster", "publishedAt": "2022-10-19T03:09:50Z", "phrases": [], "source": "Yahoo Finance", "has_report": true, "video_path": "/ytube/Yahoo Finance/2022/mHZGU7PwZTc"}, {"videoId": "05Srmmqf0dw", "channelId": "UCEAZeUIeJs0IjQiqTCdVSIg", "description": "Tesla #Teslaearnings #elonmusk #yahoofinance Yahoo Finance Live's Dave Briggs checks out Tesla's stock before its latest ...", "title": "Tesla set to report earnings after Wednesday&#39;s close", "publishedAt": "2022-10-18T23:22:09Z", "phrases": [], "source": "Yahoo Finance", "has_report": true, "video_path": "/ytube/Yahoo Finance/2022/05Srmmqf0dw"}, {"videoId": "z2589yGyHsw", "channelId": "UCEAZeUIeJs0IjQiqTCdVSIg", "description": "stockmarket #Twitter #Amylyx #yahoofinance Yahoo Finance Live's Seana Smith looks at several stocks trending in the ...", "title": "Stocks moving after hours: Twitter, Amylyx Pharmaceuticals, AutoZone, Airbnb", "publishedAt": "2022-10-18T23:15:58Z", "phrases": [], "source": "Yahoo Finance", "has_report": true, "video_path": "/ytube/Yahoo Finance/2022/z2589yGyHsw"}, {"videoId": "jzDDlqcw6dE", "channelId": "UCEAZeUIeJs0IjQiqTCdVSIg", "description": "homebuilder #realestate #yahoofinance Yahoo Finance Live anchors examines homebuilder sentiment figures reported in ...", "title": "Homebuilder sentiment falls for 10th straight month", "publishedAt": "2022-10-18T21:56:15Z", "phrases": [], "source": "Yahoo Finance", "has_report": true, "video_path": "/ytube/Yahoo Finance/2022/jzDDlqcw6dE"}, {"videoId": "BRrmnZ4CQak", "channelId": "UCEAZeUIeJs0IjQiqTCdVSIg", "description": "ElizabethHolmes #Theranos #yahoofinance Yahoo Finance legal reporter Alexis Keenan explains how Elizabeth Holmes and her ...", "title": "Elizabeth Holmes seeks a new trial on fraud conviction", "publishedAt": "2022-10-18T21:53:04Z", "phrases": [], "source": "Yahoo Finance", "has_report": true, "video_path": "/ytube/Yahoo Finance/2022/BRrmnZ4CQak"}, {"videoId": "UWNXnCFfP4w", "channelId": "UCEAZeUIeJs0IjQiqTCdVSIg", "description": "retail #yahoofinance ICSC CEO Tom McGee examines consumer spending forecasts ahead of the 2022 holiday shopping season ...", "title": "Retail has experienced \u2018a rebirth and a renaissance\u2019 throughout the pandemic: ICSC CEO", "publishedAt": "2022-10-18T21:47:59Z", "phrases": [], "source": "Yahoo Finance", "has_report": true, "video_path": "/ytube/Yahoo Finance/2022/UWNXnCFfP4w"}, {"videoId": "F2tASOBwfnw", "channelId": "UCEAZeUIeJs0IjQiqTCdVSIg", "description": "Apple #iPhone14 #ipad Yahoo Finance tech editor Dan Howley details the latest moves by Apple, which include a newly ...", "title": "Apple reportedly cuts production figures on iPhone 14 Plus, unveils redesigned iPad", "publishedAt": "2022-10-18T21:44:50Z", "phrases": [], "source": "Yahoo Finance", "has_report": true, "video_path": "/ytube/Yahoo Finance/2022/F2tASOBwfnw"}, {"videoId": "1iVTbuGfqnQ", "channelId": "UCEAZeUIeJs0IjQiqTCdVSIg", "description": "stocks #inflation #YahooFinance #recession #bitcoin #Biden #Stockmarket #coronavirus #memestocks #Fed #YahooFinance ...", "title": "Stock Market Coverage - Tuesday October 18 Yahoo Finance", "publishedAt": "2022-10-18T21:38:25Z", "phrases": ["coronavirus"], "source": "Yahoo Finance", "has_report": false}, {"videoId": "yMxPrMNqkpM", "channelId": "UCEAZeUIeJs0IjQiqTCdVSIg", "description": "FederalReserve #Fed #yahoofinance Charles Schwab Chief Fixed Income Strategist Kathy Jones joins Yahoo Finance Live ...", "title": "Fed&#39;s &#39;comfort level&#39; for wage growth is 2 to 3%: Strategist", "publishedAt": "2022-10-18T21:25:18Z", "phrases": [], "source": "Yahoo Finance", "has_report": true, "video_path": "/ytube/Yahoo Finance/2022/yMxPrMNqkpM"}, {"videoId": "OFbNeKtIJNY", "channelId": "UCEAZeUIeJs0IjQiqTCdVSIg", "description": "stocks #inflation #YahooFinance #recession #bitcoin #Biden #Stockmarket #coronavirus #memestocks #Fed #YahooFinance ...", "title": "Stock Market Coverage - Wednesday October 19 Yahoo Finance", "publishedAt": "2022-10-18T21:20:58Z", "phrases": ["coronavirus"], "source": "Yahoo Finance", "has_report": false}, {"videoId": "IPWfbuKMEnE", "channelId": "UCEAZeUIeJs0IjQiqTCdVSIg", "description": "CreditSuisse #yahoofinance Yahoo Finance reporter Alexandra Semenova details how Credit Suisse is reportedly working with ...", "title": "Credit Suisse seeks third-party financing amid restructuring", "publishedAt": "2022-10-18T21:12:39Z", "phrases": [], "source": "Yahoo Finance", "has_report": true, "video_path": "/ytube/Yahoo Finance/2022/IPWfbuKMEnE"}, {"videoId": "VlGZkjWh5DI", "channelId": "UCEAZeUIeJs0IjQiqTCdVSIg", "description": "stocks #investing #yahoofinance Stocks are moving higher for the second straight day, largely driven by earnings action, with all ...", "title": "Stocks boosted ahead of the closing bell, industrial sector leads gains", "publishedAt": "2022-10-18T21:09:29Z", "phrases": [], "source": "Yahoo Finance", "has_report": true, "video_path": "/ytube/Yahoo Finance/2022/VlGZkjWh5DI"}, {"videoId": "zUTXCroxBcU", "channelId": "UCEAZeUIeJs0IjQiqTCdVSIg", "description": "Hasbro #Hasbrostock #yahoofinance Yahoo Finance Live anchors Dave Briggs, Rachelle Akuffo and Seana Smith discuss ...", "title": "Hasbro stock slides after reporting a Q3 earnings miss", "publishedAt": "2022-10-18T21:04:47Z", "phrases": [], "source": "Yahoo Finance", "has_report": true, "video_path": "/ytube/Yahoo Finance/2022/zUTXCroxBcU"}, {"videoId": "RyxT_ZrngRY", "channelId": "UCEAZeUIeJs0IjQiqTCdVSIg", "description": "LockheedMartin #yahoofinance Shares of Lockheed Martin are moving higher after the company beat earnings expectations for ...", "title": "Lockheed Martin stock jumps after topping earnings estimates", "publishedAt": "2022-10-18T20:59:35Z", "phrases": [], "source": "Yahoo Finance", "has_report": true, "video_path": "/ytube/Yahoo Finance/2022/RyxT_ZrngRY"}, {"videoId": "lIHoMiYC1nA", "channelId": "UCEAZeUIeJs0IjQiqTCdVSIg", "description": "oil #oilprices #yahoofinance The Energy Word Founder Dan Dicker sits down with Yahoo Finance Live anchors Rachelle Akuffo ...", "title": "Oil demand could push prices to &#39;new highs above $120 a barrel&#39; in 2023: Analyst", "publishedAt": "2022-10-18T20:56:35Z", "phrases": [], "source": "Yahoo Finance", "has_report": true, "video_path": "/ytube/Yahoo Finance/2022/lIHoMiYC1nA"}, {"videoId": "yQ4NRstXM2Y", "channelId": "UCEAZeUIeJs0IjQiqTCdVSIg", "description": "Peloton #Tread+ #yahoofinance Yahoo Finance anchors Seana Smith, Dave Briggs and Rachelle Akuffo discuss Peloton ...", "title": "Peloton extends refund window for Tread+", "publishedAt": "2022-10-18T20:50:46Z", "phrases": [], "source": "Yahoo Finance", "has_report": true, "video_path": "/ytube/Yahoo Finance/2022/yQ4NRstXM2Y"}, {"videoId": "7rlG5t-aDlk", "channelId": "UCEAZeUIeJs0IjQiqTCdVSIg", "description": "stocks #closingbell #yahoofinance Yahoo Finance's Jared Blikre dives into today's market action ahead of the closing bell.", "title": "Stocks, sectors clinch gains ahead of the closing bell", "publishedAt": "2022-10-18T20:38:48Z", "phrases": [], "source": "Yahoo Finance", "has_report": true, "video_path": "/ytube/Yahoo Finance/2022/7rlG5t-aDlk"}, {"videoId": "Cbs6MPIcQQI", "channelId": "UCEAZeUIeJs0IjQiqTCdVSIg", "description": "Amazon #NFL #yahoofinance #blackfriday Yahoo Finance anchors Rachelle Akuffo, Dave Briggs and Seana Smith discuss ...", "title": "Amazon set to stream NFL Black Friday game in 2023", "publishedAt": "2022-10-18T20:36:45Z", "phrases": [], "source": "Yahoo Finance", "has_report": true, "video_path": "/ytube/Yahoo Finance/2022/Cbs6MPIcQQI"}, {"videoId": "pXRbD5IK19I", "channelId": "UCEAZeUIeJs0IjQiqTCdVSIg", "description": "whitehousepressbriefing #karinejeanpierre #yahoofinance White House Press Secretary Karine Jean-Pierre delivers the latest ...", "title": "White House Press Secretary Karine Jean-Pierre holds briefing", "publishedAt": "2022-10-18T18:57:10Z"}, {"videoId": "AhjMyHhaO48", "channelId": "UCEAZeUIeJs0IjQiqTCdVSIg", "description": "inflation #taxes #inflationreductionact #yahoofinance Tax Foundation executive vice president Daniel Bunn joins Yahoo Finance ...", "title": "Taxes: Inflation Reduction Act \u2018adds complexity to the system,\u2019 expert says", "publishedAt": "2022-10-18T18:11:16Z"}, {"videoId": "sOr3d_lAIeY", "channelId": "UCEAZeUIeJs0IjQiqTCdVSIg", "description": "Apple #holidayshopping #yahoofinance Yahoo Finance Tech Editor Dan Howley breaks down Apple's new iPads and Apple TVs ...", "title": "Apple introduces new iPads and Apple TV 4K ahead of holiday shopping", "publishedAt": "2022-10-18T18:06:22Z"}, {"videoId": "vu0pkPHsJrs", "channelId": "UCEAZeUIeJs0IjQiqTCdVSIg", "description": "Amazon #Amazonunionization #yahoofinance Yahoo Finance's Akiko Fujita reports that Amazon workers near Albany, New York, ...", "title": "Amazon workers in Albany vote against unionization", "publishedAt": "2022-10-18T18:00:25Z"}, {"videoId": "Qzd6IL0unGs", "channelId": "UCEAZeUIeJs0IjQiqTCdVSIg", "description": "China #chinaeconomy #yahoofinance Christopher Marquis, Sinyi Professor of Chinese Management at The University of ...", "title": "China\u2019s economy won\u2019t be \u2018going up anytime soon,\u2019 professor says", "publishedAt": "2022-10-18T17:58:19Z"}, {"videoId": "9yKY-w-4kyQ", "channelId": "UCEAZeUIeJs0IjQiqTCdVSIg", "description": "RollsRoyce #spectre #yahoofinance Rolls Royce Motorcars CEO Torsten Muller-Otvos speaks with Yahoo Finance's Pras ...", "title": "Rolls Royce CEO: Spectre the first EV in the \u2018ultra-luxury segment\u2019", "publishedAt": "2022-10-18T17:50:27Z"}, {"videoId": "43fFri0KS3A", "channelId": "UCEAZeUIeJs0IjQiqTCdVSIg", "description": "Johnson&Johnson #yahoofinance Yahoo Finance's Anjalee Khemlani discusses Johnson & Johnson earnings as well as the ...", "title": "Johnson &amp; Johnson beat on Q3 earnings despite inflationary pressures", "publishedAt": "2022-10-18T17:47:08Z"}, {"videoId": "uODZyHfQkGY", "channelId": "UCEAZeUIeJs0IjQiqTCdVSIg", "description": "Amazon #Amazonstock #yahoofinance Yahoo Finance's Alexis Keenan joins the Live show to discuss the expectations for ...", "title": "Amazon faces its fourth union election of the year", "publishedAt": "2022-10-18T17:42:10Z"}, {"videoId": "lL2aBFLJCqI", "channelId": "UCEAZeUIeJs0IjQiqTCdVSIg", "description": "Cash #stocks #yahoofinance Yahoo Finance Live's Akiko Fujita breaks down the chart of the day which looks at cash levels on the ...", "title": "Cash positions rise to highest level in 21 years: BofA fund managers survey", "publishedAt": "2022-10-18T17:39:08Z"}, {"videoId": "nkU4xUvctK4", "channelId": "UCEAZeUIeJs0IjQiqTCdVSIg", "description": "Intel #MobileyeIPO #yahoofinance Yahoo Finance's Daniel Howley joins the Live show to discuss Intel's $20 billion valuation for ...", "title": "Intel targets less than $20 billion valuation for Mobileye IPO", "publishedAt": "2022-10-18T17:24:32Z"}, {"videoId": "hHu1kD4M8uk", "channelId": "UCEAZeUIeJs0IjQiqTCdVSIg", "description": "Equitymarket #yahoofinance BlackRock Global Fixed Income Chief Investment Officer Rick Rieder joins Yahoo Finance Live ...", "title": "Equity market \u2018has some pretty sizable short positions,\u2019 strategist says", "publishedAt": "2022-10-18T17:21:52Z"}, {"videoId": "3zcNom6wKq4", "channelId": "UCEAZeUIeJs0IjQiqTCdVSIg", "description": "Russia #midtermelections #yahoofinance Yahoo Finance's Rick Newman joins the Live show to discuss how Russia could disrupt ...", "title": "How Russia could disrupt U.S. midterm elections", "publishedAt": "2022-10-18T17:18:42Z"}, {"videoId": "NUZYT-rRUYI", "channelId": "UCEAZeUIeJs0IjQiqTCdVSIg", "description": "stocks #Snap #yahoofinance Yahoo Finance Live's Brian Sozzi discusses a Deutsche Bank analyst's expectations for Snap stock ...", "title": "Deutsche Bank sees limited upside for Snap stock", "publishedAt": "2022-10-18T17:15:06Z"}, {"videoId": "2zRqF0GnJ84", "channelId": "UCEAZeUIeJs0IjQiqTCdVSIg", "description": "LGChem #AVEO #yahoofinance Yahoo Finance anchor Brad Smith breaks down how markets are trading, plus why AVEO stock ...", "title": "LG Chem to acquire AVEO Oncology for $566 million", "publishedAt": "2022-10-18T17:12:28Z"}, {"videoId": "rdJdIpHNjxY", "channelId": "UCEAZeUIeJs0IjQiqTCdVSIg", "description": "Chipotle #minimumwage #yahoofinance Yahoo Finance Live anchors Julie Hyman, Brian Sozzi and Brad Smith discuss Chipotle ...", "title": "Chipotle CEO says California minimum wage fight \u2018a real shame\u2019", "publishedAt": "2022-10-18T17:08:16Z"}, {"videoId": "a2I00Hf4hKo", "channelId": "UCEAZeUIeJs0IjQiqTCdVSIg", "description": "Apple #Boeing #Joby #yahoofinance Yahoo Finance anchor Julie Hyman reports the latest notable business headlines including ...", "title": "Apple workers strike, Boeing to review 737 Max 7 documents, Joby seeks air certification in Japan", "publishedAt": "2022-10-18T17:03:32Z"}, {"videoId": "iej0bNZ9YZw", "channelId": "UCEAZeUIeJs0IjQiqTCdVSIg", "description": "Biden #reproductiverights #yahoofinance U.S. President Biden delivers remarks on reproductive rights at the DNC event at the ...", "title": "LIVE: President Biden delivers remarks on reproductive rights", "publishedAt": "2022-10-18T17:03:51Z"}, {"videoId": "wWpKsNSuupI", "channelId": "UCEAZeUIeJs0IjQiqTCdVSIg", "description": "Citi #Tesla #yahoofinance Yahoo Finance Live anchors Brian Sozzi, Brad Smith and Julie Hyman discuss shares of Tesla after ...", "title": "Citi reiterates Sell rating on Tesla stock", "publishedAt": "2022-10-18T16:58:36Z"}, {"videoId": "JxdSIR2g2OM", "channelId": "UCEAZeUIeJs0IjQiqTCdVSIg", "description": "Meta #Giphy #KanyeWest #yahoofinance Yahoo Finance Anchors Brad Smith, Brian Sozzi and Julie Hyman discuss two other ...", "title": "Meta forced to sell Giphy, Kanye West to buy social media platform Parler", "publishedAt": "2022-10-18T16:39:07Z"}, {"videoId": "zq5Mh50EtMs", "channelId": "UCEAZeUIeJs0IjQiqTCdVSIg", "description": "Colgate #yahoofinance Yahoo Finance Live anchors Julie Hyman, Brian Sozzi and Brad Smith discuss activist investor Third ...", "title": "Dan Loeb\u2019s Third Point adds to stake in Colgate", "publishedAt": "2022-10-18T16:32:05Z"}, {"videoId": "mAI6LwogJPY", "channelId": "UCEAZeUIeJs0IjQiqTCdVSIg", "description": "Bankearnings #Banks #yahoofinance JMP Securities Director of Financial Technology Research Devin Ryan joins Yahoo ...", "title": "Bank earnings are \u2018really encouraging,\u2019 analyst says", "publishedAt": "2022-10-18T16:20:02Z"}, {"videoId": "bwo6cbJ3xw8", "channelId": "UCEAZeUIeJs0IjQiqTCdVSIg", "description": "President Joe Biden spoke about some of the details regarding the student loan forgiveness plan on October 17, 2022.", "title": "President Biden on student debt relief", "publishedAt": "2022-10-18T16:17:32Z"}, {"videoId": "05fMInqq7_E", "channelId": "UCEAZeUIeJs0IjQiqTCdVSIg", "description": "Target #yahoofinance Jefferies Sr. Research Analyst Corey Tarlowe joins Yahoo Finance Live to discuss upgrading Target to Buy, ...", "title": "Why Target\u2019s inventory problem may not be as bad as investors think", "publishedAt": "2022-10-18T16:14:31Z"}, {"videoId": "CMPujdpftr8", "channelId": "UCEAZeUIeJs0IjQiqTCdVSIg", "description": "crudeoil #oil #yahoofinance Yahoo Finance's Jared Blikre breaks down the moves in commodities as OPEC+ members back ...", "title": "Crude oil falls on reports the U.S. will sell oil from emergency reserves", "publishedAt": "2022-10-18T16:08:49Z"}, {"videoId": "9817yFgUNio", "channelId": "UCEAZeUIeJs0IjQiqTCdVSIg", "description": "Wedbush #Carvana #yahoofinance Yahoo Finance Live anchors Brad Smith and Brian Sozzi to discuss shares of Carvana after a ...", "title": "Wedbush downgrades Carvana to Neutral", "publishedAt": "2022-10-18T16:05:16Z"}, {"videoId": "OGKl0fsCX5k", "channelId": "UCEAZeUIeJs0IjQiqTCdVSIg", "description": "Roblox #yahoofinance Cowen Sr. Research Analyst Doug Creutz joins Yahoo Finance Live anchors Brian Sozzi and Brad Smith ...", "title": "Roblox has \u2018great content for kids but not for adults\u2019: Analyst", "publishedAt": "2022-10-18T16:01:54Z"}, {"videoId": "KRHSZlTewzE", "channelId": "UCEAZeUIeJs0IjQiqTCdVSIg", "description": "Walmart #Walmartstock #yahoofinance Yahoo Finance's Brooke DiPalma joins the Live show to discuss Walmart's plans to ...", "title": "Walmart to launch creator platform for influencers", "publishedAt": "2022-10-18T15:53:04Z"}]}