{"Version": "1.0.0", "LINES": [{"text": "have them for the first time ever Perry", "start": 26.4, "duration": 4.139, "ents": [{"label_": "ORDINAL", "text": "first"}, {"label_": "GPE", "text": "Perry"}], "sentiment": 0.25}, {"text": "sitting over and around two thousand", "start": 38.34, "duration": 4.02, "ents": [{"label_": "CARDINAL", "text": "around two thousand"}], "sentiment": 0.0}, {"text": "force investors into choosing one or the", "start": 50.039, "duration": 4.5, "ents": [{"label_": "CARDINAL", "text": "one"}], "sentiment": 0.0}, {"text": "let me get to my first question your", "start": 102.18, "duration": 5.759, "ents": [{"label_": "ORDINAL", "text": "first"}], "sentiment": 0.25}, {"text": "in uh 2016 2017 with a private company", "start": 121.14, "duration": 5.04, "ents": [], "sentiment": 0.0}, {"text": "great gold property in 2019 and when we", "start": 126.18, "duration": 5.279, "ents": [{"label_": "DATE", "text": "2019"}], "sentiment": 0.8}, {"text": "staked it we were aware there was one", "start": 129.479, "duration": 3.601, "ents": [], "sentiment": 0.25}, {"text": "sideline uh 2021 we shot a MAG survey on", "start": 139.319, "duration": 5.28, "ents": [{"label_": "CARDINAL", "text": "2021"}, {"label_": "ORG", "text": "MAG"}], "sentiment": 0.0}, {"text": "drilling at the end of 2021 and yeah", "start": 147.48, "duration": 4.5, "ents": [{"label_": "DATE", "text": "the end of 2021"}], "sentiment": 0.0}, {"text": "and one corner of what we call Zone one", "start": 154.98, "duration": 5.7, "ents": [{"label_": "CARDINAL", "text": "one"}], "sentiment": 0.0}, {"text": "in a second but let's let's stick to", "start": 171.18, "duration": 3.54, "ents": [{"label_": "ORDINAL", "text": "second"}], "sentiment": 0.0}, {"text": "this first iniquities that's on", "start": 173.16, "duration": 4.2, "ents": [{"label_": "ORDINAL", "text": "first"}], "sentiment": 0.25}, {"text": "drilled then you've hit on all 42 of", "start": 179.04, "duration": 5.64, "ents": [{"label_": "CARDINAL", "text": "42"}], "sentiment": 0.0}, {"text": "sure well a little bit of size first", "start": 198.06, "duration": 3.599, "ents": [{"label_": "ORDINAL", "text": "first"}], "sentiment": 0.1875}, {"text": "and it's about 14 kilometers long uh", "start": 203.519, "duration": 5.761, "ents": [{"label_": "QUANTITY", "text": "about 14 kilometers"}], "sentiment": -0.05}, {"text": "we've got uh two easy spots to drill two", "start": 206.4, "duration": 5.88, "ents": [{"label_": "CARDINAL", "text": "two"}, {"label_": "CARDINAL", "text": "two"}], "sentiment": 0.43333333333333335}, {"text": "great big Hills Tower about 700 feet", "start": 209.28, "duration": 5.459, "ents": [{"label_": "FAC", "text": "Hills Tower"}, {"label_": "QUANTITY", "text": "about 700 feet"}], "sentiment": 0.4}, {"text": "and Zone one and zone two they're eight", "start": 220.08, "duration": 4.86, "ents": [{"label_": "CARDINAL", "text": "two"}, {"label_": "CARDINAL", "text": "eight"}], "sentiment": 0.0}, {"text": "20 holes in each of them we hit in every", "start": 224.94, "duration": 6.24, "ents": [{"label_": "CARDINAL", "text": "20"}], "sentiment": 0.0}, {"text": "hole right from the surface so the first", "start": 227.4, "duration": 6.899, "ents": [{"label_": "ORDINAL", "text": "first"}], "sentiment": 0.26785714285714285}, {"text": "meter looks like the 30th meter uh it's", "start": 231.18, "duration": 7.08, "ents": [], "sentiment": 0.0}, {"text": "about 0.8 0.8 percent nickel uh about 20", "start": 234.299, "duration": 7.201, "ents": [{"label_": "CARDINAL", "text": "about 0.8"}, {"label_": "CARDINAL", "text": "about 20"}], "sentiment": 0.0}, {"text": "putting 40 jewels and now not hitting", "start": 257.579, "duration": 3.301, "ents": [{"label_": "CARDINAL", "text": "40"}], "sentiment": 0.0}, {"text": "two zones by the way thanks on behalf of", "start": 264.36, "duration": 3.24, "ents": [{"label_": "CARDINAL", "text": "two"}], "sentiment": 0.2}, {"text": "them Zone one and zone two instead of", "start": 267.6, "duration": 3.9, "ents": [{"label_": "CARDINAL", "text": "two"}], "sentiment": 0.0}, {"text": "they're almost 10 kilometers apart so", "start": 275.4, "duration": 4.14, "ents": [{"label_": "QUANTITY", "text": "almost 10 kilometers"}], "sentiment": 0.0}, {"text": "when they're 10 kilometers apart what", "start": 283.56, "duration": 2.94, "ents": [{"label_": "QUANTITY", "text": "10 kilometers"}], "sentiment": 0.0}, {"text": "we've gone is 129 meters uh we just", "start": 292.32, "duration": 4.379, "ents": [{"label_": "QUANTITY", "text": "129 meters"}], "sentiment": 0.0}, {"text": "actually and uh we're drilling one", "start": 296.699, "duration": 4.081, "ents": [{"label_": "CARDINAL", "text": "one"}], "sentiment": 0.0}, {"text": "that's in between the two zones we", "start": 299.1, "duration": 3.0, "ents": [{"label_": "CARDINAL", "text": "two"}], "sentiment": 0.0}, {"text": "yeah it's it's very large 14 kilometers", "start": 304.68, "duration": 4.2, "ents": [{"label_": "QUANTITY", "text": "14 kilometers"}], "sentiment": 0.2785714285714286}, {"text": "around us is gold we've got 200 square", "start": 320.04, "duration": 4.379, "ents": [{"label_": "QUANTITY", "text": "200 square"}], "sentiment": 0.0}, {"text": "property between two gold mines on Trend", "start": 324.419, "duration": 4.56, "ents": [{"label_": "CARDINAL", "text": "two"}, {"label_": "ORG", "text": "Trend"}], "sentiment": 0.0}, {"text": "project we are 45 kilometers from the", "start": 359.46, "duration": 5.76, "ents": [{"label_": "QUANTITY", "text": "45 kilometers"}], "sentiment": 0.0}, {"text": "Quinnell which is about 23 000 people", "start": 365.22, "duration": 4.02, "ents": [{"label_": "ORG", "text": "Quinnell"}, {"label_": "CARDINAL", "text": "about 23 000"}], "sentiment": 0.0}, {"text": "of Prince George which has close to 100", "start": 369.24, "duration": 4.019, "ents": [{"label_": "FAC", "text": "Prince George"}, {"label_": "CARDINAL", "text": "close to 100"}], "sentiment": 0.0}, {"text": "000 people I thought you were Prince", "start": 371.88, "duration": 4.379, "ents": [{"label_": "CARDINAL", "text": "000"}], "sentiment": 0.0}, {"text": "George anyway uh it's uh basically 45", "start": 373.259, "duration": 5.461, "ents": [{"label_": "CARDINAL", "text": "45"}], "sentiment": 0.0}, {"text": "Highway 26 and then uh you zoom off for", "start": 378.72, "duration": 5.699, "ents": [], "sentiment": 0.0}, {"text": "about 15 kilometers on a well improved", "start": 381.72, "duration": 5.099, "ents": [{"label_": "QUANTITY", "text": "about 15 kilometers"}], "sentiment": 0.0}, {"text": "shop in Cornell at uh you know at eight", "start": 396.9, "duration": 4.98, "ents": [{"label_": "GPE", "text": "Cornell"}, {"label_": "CARDINAL", "text": "eight"}], "sentiment": 0.0}, {"text": "o'clock and by 8 45 they're standing at", "start": 399.66, "duration": 5.28, "ents": [{"label_": "CARDINAL", "text": "8 45"}], "sentiment": 0.0}, {"text": "to 200 000 ounces per year it's the old", "start": 420.18, "duration": 4.019, "ents": [{"label_": "QUANTITY", "text": "200 000 ounces"}], "sentiment": 0.1}, {"text": "just raised 52 million dollars on that", "start": 424.199, "duration": 4.44, "ents": [{"label_": "MONEY", "text": "52 million dollars"}], "sentiment": 0.0}, {"text": "problem raising money for that one uh", "start": 428.639, "duration": 3.721, "ents": [{"label_": "CARDINAL", "text": "one"}], "sentiment": 0.0}, {"text": "19 and in August of 19 we closed it and", "start": 437.34, "duration": 5.52, "ents": [{"label_": "CARDINAL", "text": "19"}, {"label_": "DATE", "text": "August"}, {"label_": "CARDINAL", "text": "19"}], "sentiment": -0.1}, {"text": "in September of 19 with unbelievably", "start": 440.16, "duration": 4.86, "ents": [{"label_": "DATE", "text": "September of 19"}], "sentiment": -0.25}, {"text": "Barkerville gold mines for 335 million", "start": 445.02, "duration": 4.14, "ents": [{"label_": "ORG", "text": "Barkerville"}, {"label_": "CARDINAL", "text": "335 million"}], "sentiment": 0.0}, {"text": "1865 was the largest Community West of", "start": 489.319, "duration": 5.38, "ents": [{"label_": "DATE", "text": "1865"}], "sentiment": 0.0}, {"text": "North America there were five thousand", "start": 494.699, "duration": 3.481, "ents": [{"label_": "LOC", "text": "North America"}, {"label_": "CARDINAL", "text": "five thousand"}], "sentiment": 0.0}, {"text": "Cisco changed that in 2019 they came up", "start": 505.259, "duration": 4.021, "ents": [{"label_": "ORG", "text": "Cisco"}, {"label_": "DATE", "text": "2019"}], "sentiment": 0.0}, {"text": "five holes we're drilling them with a a", "start": 532.38, "duration": 4.44, "ents": [{"label_": "CARDINAL", "text": "five"}], "sentiment": 0.0}, {"text": "River from as well so it's a 6 000", "start": 548.1, "duration": 4.44, "ents": [{"label_": "CARDINAL", "text": "6 000"}], "sentiment": 0.0}, {"text": "drive the program uh we're doing five", "start": 562.98, "duration": 3.96, "ents": [{"label_": "CARDINAL", "text": "five"}], "sentiment": 0.0}, {"text": "150 meters each that'll take a few weeks", "start": 566.94, "duration": 4.56, "ents": [{"label_": "QUANTITY", "text": "150 meters"}, {"label_": "DATE", "text": "a few weeks"}], "sentiment": -0.2}, {"text": "program we're going to drill 20 holes", "start": 574.98, "duration": 4.2, "ents": [{"label_": "CARDINAL", "text": "20"}], "sentiment": 0.0}, {"text": "that will go down about 300 meters using", "start": 577.08, "duration": 3.96, "ents": [{"label_": "QUANTITY", "text": "about 300 meters"}], "sentiment": -0.15555555555555559}, {"text": "probably about 100 days realistically", "start": 583.5, "duration": 4.56, "ents": [{"label_": "DATE", "text": "about 100 days"}], "sentiment": 0.0}, {"text": "guys raise almost six hundred thousand", "start": 589.92, "duration": 3.18, "ents": [{"label_": "CARDINAL", "text": "almost six hundred thousand"}], "sentiment": 0.0}, {"text": "know for two years nobody was asking me", "start": 606.12, "duration": 3.42, "ents": [{"label_": "DATE", "text": "two years"}], "sentiment": 0.0}, {"text": "94 square kilometers we've now got over", "start": 617.399, "duration": 3.901, "ents": [{"label_": "QUANTITY", "text": "94 square kilometers"}], "sentiment": 0.0}, {"text": "200 square kilometers that is in between", "start": 619.2, "duration": 3.54, "ents": [{"label_": "QUANTITY", "text": "200 square kilometers"}], "sentiment": 0.0}, {"text": "two gold mines because we've got", "start": 621.3, "duration": 3.3, "ents": [{"label_": "CARDINAL", "text": "two"}], "sentiment": 0.0}, {"text": "bottom and that one's about 27 owned by", "start": 640.68, "duration": 4.02, "ents": [{"label_": "CARDINAL", "text": "about 27"}], "sentiment": 0.0}, {"text": "second largest open pit copper mine this", "start": 654.6, "duration": 5.1, "ents": [{"label_": "ORDINAL", "text": "second"}], "sentiment": 0.0}, {"text": "is probably uh all within uh you know 60", "start": 659.7, "duration": 6.0, "ents": [{"label_": "CARDINAL", "text": "60"}], "sentiment": 0.0}, {"text": "has produced over four million ounce of", "start": 670.079, "duration": 3.781, "ents": [{"label_": "QUANTITY", "text": "four million ounce"}], "sentiment": 0.0}, {"text": "got uh Cisco's putting in three-phase", "start": 695.279, "duration": 4.141, "ents": [{"label_": "ORG", "text": "Cisco"}, {"label_": "CARDINAL", "text": "three"}], "sentiment": 0.0}, {"text": "power that'll go about 15 kilometers", "start": 696.959, "duration": 3.961, "ents": [{"label_": "QUANTITY", "text": "about 15 kilometers"}], "sentiment": 0.0}, {"text": "three-phase power liner uh we've got", "start": 700.92, "duration": 4.32, "ents": [{"label_": "CARDINAL", "text": "three"}], "sentiment": 0.0}, {"text": "highway 97. it's a main north south", "start": 705.24, "duration": 3.96, "ents": [{"label_": "CARDINAL", "text": "97"}], "sentiment": 0.16666666666666666}, {"text": "fabulous so we went up there uh in 2016", "start": 854.639, "duration": 5.88, "ents": [{"label_": "DATE", "text": "2016"}], "sentiment": 0.4}, {"text": "that in 2016-17 it realized very quickly", "start": 863.399, "duration": 5.341, "ents": [{"label_": "DATE", "text": "2016-17"}], "sentiment": 0.43333333333333335}, {"text": "six thousand square foot building but", "start": 874.74, "duration": 2.76, "ents": [{"label_": "QUANTITY", "text": "six thousand square foot"}], "sentiment": 0.0}, {"text": "Green River Gold going in 2017 and we", "start": 883.92, "duration": 5.159, "ents": [{"label_": "DATE", "text": "2017"}], "sentiment": -0.2}, {"text": "didn't pick up our first property until", "start": 887.339, "duration": 4.62, "ents": [{"label_": "ORDINAL", "text": "first"}], "sentiment": 0.25}, {"text": "March of 19th so we it wasn't that we", "start": 889.079, "duration": 4.32, "ents": [{"label_": "DATE", "text": "March of 19th"}], "sentiment": 0.0}, {"text": "for about 40 years uh knows everything", "start": 914.94, "duration": 4.5, "ents": [{"label_": "DATE", "text": "about 40 years"}], "sentiment": 0.0}, {"text": "looking for one thing and they found", "start": 963.779, "duration": 3.18, "ents": [{"label_": "CARDINAL", "text": "one"}], "sentiment": 0.0}, {"text": "rent for that six thousand square foot", "start": 1002.66, "duration": 3.66, "ents": [{"label_": "QUANTITY", "text": "six thousand square foot"}], "sentiment": 0.0}, {"text": "building that's just you know like a two", "start": 1004.279, "duration": 3.841, "ents": [{"label_": "CARDINAL", "text": "two"}], "sentiment": 0.0}, {"text": "you talked about how you guys were first", "start": 1042.74, "duration": 5.28, "ents": [{"label_": "ORDINAL", "text": "first"}], "sentiment": 0.25}, {"text": "up there 2015-16 look for Placer then", "start": 1044.78, "duration": 6.0, "ents": [{"label_": "DATE", "text": "2015-16"}, {"label_": "ORG", "text": "Placer"}], "sentiment": 0.0}, {"text": "just as gold is broken through 2000 and", "start": 1055.0, "duration": 6.28, "ents": [{"label_": "DATE", "text": "2000"}], "sentiment": -0.4}, {"text": "hit overdrive now because three or four", "start": 1071.0, "duration": 4.98, "ents": [{"label_": "CARDINAL", "text": "three"}, {"label_": "CARDINAL", "text": "four"}], "sentiment": 0.0}, {"text": "to erupt in 2016. so I'm a little", "start": 1095.78, "duration": 3.66, "ents": [{"label_": "DATE", "text": "2016"}], "sentiment": -0.1875}, {"text": "1600 uh you know square or about 16", "start": 1159.5, "duration": 6.36, "ents": [{"label_": "CARDINAL", "text": "1600"}, {"label_": "CARDINAL", "text": "about 16"}], "sentiment": 0.0}, {"text": "so we've got that one as well and uh", "start": 1170.299, "duration": 4.861, "ents": [], "sentiment": 0.0}, {"text": "and that's another one that we think is", "start": 1189.559, "duration": 4.261, "ents": [], "sentiment": 0.0}, {"text": "eye on it for a while and it's about 10", "start": 1216.559, "duration": 3.781, "ents": [{"label_": "CARDINAL", "text": "about 10"}], "sentiment": 0.0}, {"text": "three hours from our shop so again very", "start": 1220.34, "duration": 3.839, "ents": [{"label_": "TIME", "text": "three hours"}], "sentiment": 0.2}, {"text": "River meet it's about seven half hour", "start": 1236.299, "duration": 5.521, "ents": [{"label_": "DATE", "text": "about seven half hour"}], "sentiment": -0.16666666666666666}, {"text": "straight uphill so 85 kilometers you hit", "start": 1252.62, "duration": 4.2, "ents": [{"label_": "QUANTITY", "text": "85 kilometers"}], "sentiment": 0.2}, {"text": "and you're 2500 feet higher by the time", "start": 1256.82, "duration": 4.32, "ents": [{"label_": "QUANTITY", "text": "2500 feet"}], "sentiment": 0.25}, {"text": "they were still drilling four or five", "start": 1263.919, "duration": 3.88, "ents": [{"label_": "CARDINAL", "text": "four"}], "sentiment": 0.0}, {"text": "another one uh just three hours ago uh", "start": 1273.679, "duration": 4.5, "ents": [{"label_": "CARDINAL", "text": "one"}, {"label_": "TIME", "text": "just three hours ago"}], "sentiment": 0.0}, {"text": "or three or five days ago rather we", "start": 1276.32, "duration": 4.739, "ents": [{"label_": "DATE", "text": "three or five days ago"}], "sentiment": 0.0}, {"text": "staked it and uh it's a three hour drive", "start": 1278.179, "duration": 6.601, "ents": [{"label_": "TIME", "text": "three hour"}], "sentiment": 0.0}, {"text": "little town called Hundred Mile House", "start": 1284.78, "duration": 4.56, "ents": [{"label_": "ORG", "text": "Hundred Mile House"}], "sentiment": -0.1875}, {"text": "1819 we managed to pick up the 10 square", "start": 1324.34, "duration": 5.92, "ents": [{"label_": "CARDINAL", "text": "1819"}, {"label_": "QUANTITY", "text": "10 square"}], "sentiment": 0.0}, {"text": "you 2890 give you a good thousand dollar", "start": 1340.22, "duration": 6.12, "ents": [{"label_": "CARDINAL", "text": "2890"}], "sentiment": 0.7}, {"text": "you know 65 profit on that right here", "start": 1343.159, "duration": 5.4, "ents": [{"label_": "CARDINAL", "text": "65"}], "sentiment": 0.2857142857142857}, {"text": "that for 65 I'll take it off your hands", "start": 1348.559, "duration": 5.281, "ents": [{"label_": "CARDINAL", "text": "65"}], "sentiment": 0.0}, {"text": "talk about some other things but one", "start": 1367.039, "duration": 2.88, "ents": [{"label_": "CARDINAL", "text": "one"}], "sentiment": -0.125}, {"text": "three billion dollar market I believe or", "start": 1382.76, "duration": 4.68, "ents": [{"label_": "MONEY", "text": "three billion dollar"}], "sentiment": 0.0}, {"text": "a portion of what we call Zone one was", "start": 1397.039, "duration": 5.281, "ents": [], "sentiment": 0.0}, {"text": "probably one percent of the overall", "start": 1410.659, "duration": 4.681, "ents": [{"label_": "PERCENT", "text": "one percent"}], "sentiment": 0.0}, {"text": "Plastics rubber there's just a million", "start": 1421.159, "duration": 4.561, "ents": [], "sentiment": 0.0}, {"text": "solvents so it's about a three billion", "start": 1425.72, "duration": 5.04, "ents": [{"label_": "MONEY", "text": "three billion"}], "sentiment": 0.0}, {"text": "Paper stuff because there are five Mills", "start": 1433.039, "duration": 4.561, "ents": [{"label_": "CARDINAL", "text": "five"}], "sentiment": 0.0}, {"text": "that area zone one it's in the first", "start": 1457.88, "duration": 5.52, "ents": [{"label_": "ORDINAL", "text": "first"}], "sentiment": 0.25}, {"text": "drill core the first meter of drill core", "start": 1463.4, "duration": 5.34, "ents": [{"label_": "ORDINAL", "text": "first"}], "sentiment": 0.25}, {"text": "even in the first 60 feet we average", "start": 1472.58, "duration": 4.5, "ents": [{"label_": "QUANTITY", "text": "60 feet"}], "sentiment": 0.05}, {"text": "about 50 percent talc and once you get", "start": 1474.38, "duration": 3.84, "ents": [{"label_": "PERCENT", "text": "about 50 percent"}], "sentiment": 0.0}, {"text": "of us have any ideas fifty percent good", "start": 1478.22, "duration": 5.4, "ents": [{"label_": "PERCENT", "text": "fifty percent"}], "sentiment": 0.7}, {"text": "down below 50 below about 40 feet", "start": 1485.48, "duration": 4.74, "ents": [], "sentiment": -0.15555555555555559}, {"text": "80 to 95 percent talc once you get below", "start": 1492.98, "duration": 4.8, "ents": [{"label_": "PERCENT", "text": "80 to 95 percent"}], "sentiment": 0.0}, {"text": "milled talc cells for an average of 270", "start": 1505.88, "duration": 6.539, "ents": [{"label_": "CARDINAL", "text": "270"}], "sentiment": -0.15}, {"text": "we've gone down 129 meters so far and", "start": 1519.32, "duration": 4.739, "ents": [{"label_": "QUANTITY", "text": "129 meters"}], "sentiment": -0.02777777777777779}, {"text": "this the top of the 700 foot Hill right", "start": 1537.38, "duration": 5.399, "ents": [{"label_": "QUANTITY", "text": "700 foot"}, {"label_": "ORG", "text": "Hill"}], "sentiment": 0.39285714285714285}, {"text": "have to scrape off a 700 foot Hill first", "start": 1542.779, "duration": 5.4, "ents": [{"label_": "QUANTITY", "text": "700 foot"}, {"label_": "ORG", "text": "Hill"}, {"label_": "ORDINAL", "text": "first"}], "sentiment": 0.25}, {"text": "and we drilled it we drilled there first", "start": 1561.74, "duration": 4.14, "ents": [{"label_": "ORDINAL", "text": "first"}], "sentiment": 0.25}, {"text": "was so the first place we went was to", "start": 1569.36, "duration": 4.62, "ents": [{"label_": "ORDINAL", "text": "first"}], "sentiment": 0.25}, {"text": "that we have uh you know 0.15.16 nickel", "start": 1573.98, "duration": 6.9, "ents": [], "sentiment": 0.0}, {"text": "there's at least one mine that mines", "start": 1580.88, "duration": 4.679, "ents": [{"label_": "CARDINAL", "text": "at least one"}], "sentiment": -0.3}, {"text": "imagine 0.2 percent nickel okay just for", "start": 1590.0, "duration": 5.9, "ents": [{"label_": "PERCENT", "text": "0.2 percent"}], "sentiment": 0.5}, {"text": "99.8 of your mining operation okay", "start": 1595.9, "duration": 5.86, "ents": [{"label_": "CARDINAL", "text": "99.8"}], "sentiment": 0.5}, {"text": "picture this one where let's just round", "start": 1601.76, "duration": 4.86, "ents": [], "sentiment": -0.2}, {"text": "the nickel up and say point two percent", "start": 1604.82, "duration": 3.959, "ents": [{"label_": "PERCENT", "text": "two percent"}], "sentiment": 0.0}, {"text": "say we got point two percent nickel", "start": 1610.82, "duration": 4.739, "ents": [{"label_": "PERCENT", "text": "two percent"}], "sentiment": 0.0}, {"text": "99.8 percent of our weight waste rock", "start": 1613.059, "duration": 5.74, "ents": [{"label_": "PERCENT", "text": "99.8 percent"}], "sentiment": -0.2}, {"text": "be a great summer great 2023 for Green", "start": 1632.24, "duration": 4.62, "ents": [{"label_": "DATE", "text": "2023"}], "sentiment": 0.46666666666666673}, {"text": "tell us 12 months from now that we", "start": 1756.26, "duration": 2.88, "ents": [{"label_": "DATE", "text": "12 months from now"}], "sentiment": 0.0}], "VIDEO_ID": "gsPrU5t_N1M", "VIDEO_DATA": [{"videoId": "gsPrU5t_N1M", "channelId": "UCxiA6FAQm7rPqb2Gl9pJ1-Q", "description": "Green River Gold $CCR Provides Investors With Exposure To Both Gold & Battery Metals Thanks To Impressive B.C. Projects In ...", "title": "Green River Gold $CCR Provides Investors With Exposure To Both Gold &amp; Battery Metals", "publishedAt": "2023-04-24T22:58:42Z"}, {"videoId": "K-RKgbFKrek", "channelId": "UCxiA6FAQm7rPqb2Gl9pJ1-Q", "description": "Alkaline Fuel Cell Power $PWWR $ALKFF is a clean tech energy company that provides renewable energy focused investors with ...", "title": "$PWWR Signs 4th LOI And 1st With Utility Company To Pilot Hydrogen Fuel Cell", "publishedAt": "2023-04-24T22:34:29Z"}]}