{"Version": "1.0.0", "LINES": [{"text": "rates rotator cuffs are anywhere from 40", "start": 67.6, "duration": 6.72, "ents": [{"label_": "CARDINAL", "text": "40"}], "sentiment": 0.0}, {"text": "to 95 meniscus 20 to 40 cartilage 15 to", "start": 70.08, "duration": 5.76, "ents": [{"label_": "CARDINAL", "text": "95"}, {"label_": "CARDINAL", "text": "20 to 40"}, {"label_": "CARDINAL", "text": "15"}], "sentiment": 0.0}, {"text": "35", "start": 74.32, "duration": 3.28, "ents": [{"label_": "CARDINAL", "text": "35"}], "sentiment": 0.0}, {"text": "say it's a massive 10 billion dollar", "start": 100.159, "duration": 5.201, "ents": [{"label_": "MONEY", "text": "10 billion dollar"}], "sentiment": 0.0}, {"text": "alone uh there are six hundred thousand", "start": 105.36, "duration": 4.88, "ents": [{"label_": "CARDINAL", "text": "six hundred thousand"}], "sentiment": 0.0}, {"text": "1.2 annual surgery so it's a massive", "start": 110.24, "duration": 6.559, "ents": [{"label_": "CARDINAL", "text": "1.2"}, {"label_": "DATE", "text": "annual"}], "sentiment": 0.0}, {"text": "this is uh one that we hope to explore", "start": 136.319, "duration": 4.0, "ents": [], "sentiment": 0.0}, {"text": "two three years just give us a little", "start": 166.16, "duration": 4.24, "ents": [{"label_": "DATE", "text": "two three years"}], "sentiment": -0.1875}, {"text": "and in 2017 fda basically said look", "start": 206.879, "duration": 5.28, "ents": [{"label_": "DATE", "text": "2017"}, {"label_": "ORG", "text": "fda"}], "sentiment": 0.0}, {"text": "tissue repair so i guess the first thing", "start": 294.8, "duration": 4.0, "ents": [{"label_": "ORDINAL", "text": "first"}], "sentiment": 0.25}, {"text": "just a little bit of uh the first part i", "start": 325.759, "duration": 3.761, "ents": [{"label_": "ORDINAL", "text": "first"}], "sentiment": 0.03125}, {"text": "seven and ten million bucks uh and uh", "start": 346.4, "duration": 3.68, "ents": [{"label_": "QUANTITY", "text": "seven and ten million bucks"}], "sentiment": 0.0}, {"text": "about 20 million dollars has been", "start": 348.72, "duration": 4.16, "ents": [{"label_": "MONEY", "text": "about 20 million dollars"}], "sentiment": 0.0}, {"text": "five or six years", "start": 352.88, "duration": 3.92, "ents": [{"label_": "DATE", "text": "five or six years"}], "sentiment": 0.0}, {"text": "um and uh we're focused on the 12", "start": 354.479, "duration": 4.16, "ents": [{"label_": "CARDINAL", "text": "12"}], "sentiment": 0.0}, {"text": "billion dollar as you pointed out point", "start": 356.8, "duration": 4.16, "ents": [], "sentiment": 0.0}, {"text": "12 billion dollar soft tissue market um", "start": 358.639, "duration": 4.4, "ents": [{"label_": "MONEY", "text": "12 billion dollar"}], "sentiment": 0.1}, {"text": "the first uh", "start": 444.56, "duration": 4.4, "ents": [{"label_": "ORDINAL", "text": "first"}], "sentiment": 0.25}, {"text": "we're the first organization to do a prp", "start": 446.0, "duration": 4.8, "ents": [{"label_": "ORDINAL", "text": "first"}], "sentiment": 0.25}, {"text": "mentioned it uh george about 11 million", "start": 472.319, "duration": 5.6, "ents": [], "sentiment": 0.0}, {"text": "and about three and a half million", "start": 481.52, "duration": 3.44, "ents": [{"label_": "CARDINAL", "text": "about three and a half million"}], "sentiment": -0.16666666666666666}, {"text": "third point's a little more subtle but", "start": 495.199, "duration": 4.241, "ents": [{"label_": "ORDINAL", "text": "third"}], "sentiment": -0.005208333333333329}, {"text": "the first part the second part is then", "start": 506.479, "duration": 4.481, "ents": [{"label_": "ORDINAL", "text": "first"}, {"label_": "ORDINAL", "text": "second"}], "sentiment": 0.125}, {"text": "years and years about 10 years", "start": 525.76, "duration": 4.56, "ents": [], "sentiment": 0.0}, {"text": "the fact that about a 10 billion dollar", "start": 563.76, "duration": 4.16, "ents": [{"label_": "MONEY", "text": "10 billion dollar"}], "sentiment": 0.0}, {"text": "about 600 000 surgeries as you mentioned", "start": 567.92, "duration": 5.359, "ents": [{"label_": "CARDINAL", "text": "about 600 000"}], "sentiment": 0.0}, {"text": "8 million injuries for the tendons and", "start": 570.72, "duration": 5.36, "ents": [{"label_": "CARDINAL", "text": "8 million"}], "sentiment": 0.0}, {"text": "in your knee uh about uh half a million", "start": 576.08, "duration": 5.04, "ents": [], "sentiment": -0.16666666666666666}, {"text": "surgeries a year um assuming about a two", "start": 578.48, "duration": 4.96, "ents": [{"label_": "CARDINAL", "text": "two"}], "sentiment": 0.0}, {"text": "thousand dollar price for our technology", "start": 581.12, "duration": 4.719, "ents": [], "sentiment": 0.0}, {"text": "uh that's uh again about a ten billion", "start": 583.44, "duration": 4.399, "ents": [], "sentiment": 0.0}, {"text": "over time does it grow at three or four", "start": 596.08, "duration": 4.64, "ents": [{"label_": "CARDINAL", "text": "three or four"}], "sentiment": 0.0}, {"text": "percent a year from actually ten years", "start": 598.24, "duration": 4.159, "ents": [{"label_": "DATE", "text": "ten years"}], "sentiment": 0.0}, {"text": "and they put it over the next seven", "start": 610.079, "duration": 3.841, "ents": [{"label_": "DATE", "text": "the next seven"}], "sentiment": 0.0}, {"text": "years at uh about seven percent kegger", "start": 611.839, "duration": 5.281, "ents": [], "sentiment": 0.0}, {"text": "good large so every 10 years the market", "start": 617.12, "duration": 4.64, "ents": [], "sentiment": 0.45714285714285713}, {"text": "so by the end of this decade it's a 20", "start": 621.76, "duration": 4.16, "ents": [{"label_": "DATE", "text": "the end of this decade"}, {"label_": "CARDINAL", "text": "20"}], "sentiment": 0.0}, {"text": "billion dollar market that's right", "start": 623.6, "duration": 5.04, "ents": [], "sentiment": 0.2857142857142857}, {"text": "20 to 95 that's 20 to 95", "start": 655.36, "duration": 5.28, "ents": [{"label_": "CARDINAL", "text": "20 to 95"}, {"label_": "CARDINAL", "text": "20 to"}], "sentiment": 0.0}, {"text": "tears fast it's usually uh three or four", "start": 667.68, "duration": 4.32, "ents": [{"label_": "CARDINAL", "text": "three or"}, {"label_": "CARDINAL", "text": "four"}], "sentiment": -0.024999999999999994}, {"text": "an average of 30 percent and", "start": 702.0, "duration": 3.76, "ents": [{"label_": "PERCENT", "text": "30 percent"}], "sentiment": -0.15}, {"text": "tendinopathy an average about 25 percent", "start": 703.279, "duration": 4.881, "ents": [{"label_": "PERCENT", "text": "about 25 percent"}], "sentiment": -0.15}, {"text": "and you see that all those three are the", "start": 730.399, "duration": 3.361, "ents": [{"label_": "CARDINAL", "text": "three"}], "sentiment": 0.0}, {"text": "all three of those markets", "start": 737.519, "duration": 3.44, "ents": [{"label_": "CARDINAL", "text": "three"}], "sentiment": 0.0}, {"text": "those two other products but what we're", "start": 750.24, "duration": 3.279, "ents": [{"label_": "CARDINAL", "text": "two"}], "sentiment": -0.125}, {"text": "that's the first thing you notice is", "start": 785.04, "duration": 3.68, "ents": [{"label_": "ORDINAL", "text": "first"}], "sentiment": 0.25}, {"text": "to bring uh blood first they just", "start": 802.8, "duration": 4.159, "ents": [{"label_": "ORDINAL", "text": "first"}], "sentiment": 0.25}, {"text": "actually whole blood was the first thing", "start": 805.519, "duration": 4.801, "ents": [{"label_": "ORDINAL", "text": "first"}], "sentiment": 0.225}, {"text": "four to six weeks do not move", "start": 831.6, "duration": 4.96, "ents": [{"label_": "DATE", "text": "four to six weeks"}], "sentiment": 0.0}, {"text": "that's the picture tells a thousand", "start": 854.8, "duration": 3.92, "ents": [{"label_": "CARDINAL", "text": "a thousand"}], "sentiment": 0.0}, {"text": "prp is about 10 of your blood", "start": 924.24, "duration": 5.279, "ents": [{"label_": "CARDINAL", "text": "about 10"}], "sentiment": 0.0}, {"text": "five times more platelets uh than other", "start": 941.279, "duration": 4.961, "ents": [{"label_": "CARDINAL", "text": "five"}], "sentiment": 0.1875}, {"text": "talk about the other parts in a second", "start": 962.8, "duration": 4.0, "ents": [{"label_": "ORDINAL", "text": "second"}], "sentiment": -0.0625}, {"text": "yourself uh first thing that happens is", "start": 987.04, "duration": 5.44, "ents": [{"label_": "ORDINAL", "text": "first"}], "sentiment": 0.25}, {"text": "stays on site for three four hours uh", "start": 1016.72, "duration": 5.44, "ents": [{"label_": "TIME", "text": "three four hours"}], "sentiment": 0.0}, {"text": "maximum 24 hours and then it dissipates", "start": 1019.6, "duration": 5.599, "ents": [{"label_": "TIME", "text": "24 hours"}], "sentiment": 0.0}, {"text": "used prp you have to go back three or", "start": 1031.36, "duration": 4.64, "ents": [{"label_": "CARDINAL", "text": "three"}], "sentiment": 0.0}, {"text": "four five ten times uh with your uh", "start": 1033.199, "duration": 5.441, "ents": [{"label_": "DATE", "text": "four five ten"}], "sentiment": 0.0}, {"text": "uh it's been around for 30 years", "start": 1056.799, "duration": 4.0, "ents": [{"label_": "DATE", "text": "30 years"}], "sentiment": 0.0}, {"text": "surgery and the three together so three", "start": 1143.039, "duration": 5.041, "ents": [{"label_": "CARDINAL", "text": "three"}, {"label_": "CARDINAL", "text": "three"}], "sentiment": 0.0}, {"text": "uh but the three together uh uh", "start": 1148.08, "duration": 5.12, "ents": [{"label_": "CARDINAL", "text": "three"}], "sentiment": 0.0}, {"text": "and just recently uh about uh three", "start": 1151.12, "duration": 4.4, "ents": [{"label_": "CARDINAL", "text": "about uh three"}], "sentiment": 0.0}, {"text": "uh for the combination of the three and", "start": 1156.72, "duration": 3.68, "ents": [{"label_": "CARDINAL", "text": "three"}], "sentiment": 0.0}, {"text": "you're gonna go to sleep 99 of us but", "start": 1192.32, "duration": 5.12, "ents": [{"label_": "CARDINAL", "text": "99"}], "sentiment": 0.0}, {"text": "the way presented here one plus two", "start": 1194.64, "duration": 6.72, "ents": [{"label_": "CARDINAL", "text": "one"}, {"label_": "CARDINAL", "text": "two"}], "sentiment": 0.0}, {"text": "equals three we can so so phil let", "start": 1197.44, "duration": 6.479, "ents": [{"label_": "CARDINAL", "text": "three"}], "sentiment": 0.0}, {"text": "six minutes more than the procedure", "start": 1246.559, "duration": 2.721, "ents": [{"label_": "TIME", "text": "six minutes"}], "sentiment": 0.5}, {"text": "and it stays on for six weeks at least", "start": 1256.559, "duration": 6.721, "ents": [{"label_": "DATE", "text": "six weeks"}], "sentiment": -0.3}, {"text": "about 12 10 to 12 times longer", "start": 1263.28, "duration": 5.2, "ents": [{"label_": "CARDINAL", "text": "about 12 10 to 12"}], "sentiment": 0.0}, {"text": "right so that's the magic so for six", "start": 1268.48, "duration": 4.4, "ents": [{"label_": "CARDINAL", "text": "six"}], "sentiment": 0.39285714285714285}, {"text": "and lo and behold the third one", "start": 1324.559, "duration": 4.24, "ents": [{"label_": "ORDINAL", "text": "third"}], "sentiment": 0.0}, {"text": "and what you see is about uh eighty", "start": 1330.48, "duration": 4.48, "ents": [{"label_": "CARDINAL", "text": "eighty"}], "sentiment": 0.0}, {"text": "literally running 10 seconds later", "start": 1380.799, "duration": 5.281, "ents": [{"label_": "TIME", "text": "10 seconds later"}], "sentiment": 0.0}, {"text": "two months after the the moratorium was", "start": 1472.88, "duration": 5.6, "ents": [{"label_": "DATE", "text": "two months"}], "sentiment": 0.0}, {"text": "one", "start": 1480.32, "duration": 2.16, "ents": [{"label_": "CARDINAL", "text": "one"}], "sentiment": 0.0}, {"text": "1-2 trial so we're going to combine the", "start": 1491.84, "duration": 6.16, "ents": [{"label_": "CARDINAL", "text": "1"}], "sentiment": 0.0}, {"text": "safety studies and the first", "start": 1494.799, "duration": 5.201, "ents": [{"label_": "ORDINAL", "text": "first"}], "sentiment": 0.25}, {"text": "combined the two that's also a nice", "start": 1500.0, "duration": 3.36, "ents": [{"label_": "CARDINAL", "text": "two"}], "sentiment": 0.6}, {"text": "very strongly that after the phase two", "start": 1531.12, "duration": 4.08, "ents": [{"label_": "CARDINAL", "text": "two"}], "sentiment": 0.5633333333333334}, {"text": "powered as 78 70", "start": 1536.96, "duration": 4.719, "ents": [{"label_": "DATE", "text": "78 70"}], "sentiment": 0.0}, {"text": "75 patients in this trial this is not", "start": 1539.36, "duration": 4.16, "ents": [{"label_": "CARDINAL", "text": "75"}], "sentiment": 0.0}, {"text": "well uh that's a two-way street right uh", "start": 1587.36, "duration": 5.36, "ents": [{"label_": "CARDINAL", "text": "two"}], "sentiment": 0.2857142857142857}, {"text": "trial there are 10", "start": 1625.679, "duration": 2.961, "ents": [{"label_": "CARDINAL", "text": "10"}], "sentiment": 0.0}, {"text": "six of those sites four of them has been", "start": 1631.36, "duration": 4.4, "ents": [{"label_": "CARDINAL", "text": "six"}, {"label_": "CARDINAL", "text": "four"}], "sentiment": 0.0}, {"text": "uh two more initiation visits are", "start": 1637.2, "duration": 3.839, "ents": [{"label_": "CARDINAL", "text": "two"}], "sentiment": 0.5}, {"text": "planned over the next two weeks so we'll", "start": 1638.88, "duration": 4.96, "ents": [{"label_": "DATE", "text": "the next two weeks"}], "sentiment": 0.0}, {"text": "have a full six sites up and running in", "start": 1641.039, "duration": 4.321, "ents": [{"label_": "CARDINAL", "text": "six"}], "sentiment": 0.35}, {"text": "and all 10 sites certainly by mid-july", "start": 1645.36, "duration": 4.88, "ents": [{"label_": "CARDINAL", "text": "10"}, {"label_": "DATE", "text": "mid-july"}], "sentiment": 0.21428571428571427}, {"text": "scheduled surgeries for six to eight", "start": 1658.72, "duration": 3.439, "ents": [{"label_": "CARDINAL", "text": "six to eight"}], "sentiment": 0.0}, {"text": "coming in four weeks do you want to be", "start": 1673.36, "duration": 3.84, "ents": [{"label_": "DATE", "text": "four weeks"}], "sentiment": 0.0}, {"text": "first quarter next year we'll have", "start": 1688.72, "duration": 3.439, "ents": [{"label_": "DATE", "text": "first quarter next year"}], "sentiment": 0.125}, {"text": "there is a one-year follow-up in the", "start": 1692.159, "duration": 2.801, "ents": [{"label_": "DATE", "text": "one-year"}], "sentiment": 0.0}, {"text": "and tell two friends we're going to tell", "start": 1732.88, "duration": 3.279, "ents": [{"label_": "CARDINAL", "text": "two"}], "sentiment": 0.0}, {"text": "two friends say hey we got something", "start": 1734.48, "duration": 2.4, "ents": [{"label_": "CARDINAL", "text": "two"}], "sentiment": 0.0}, {"text": "one two clinical trials we're going to", "start": 1756.08, "duration": 4.64, "ents": [{"label_": "CARDINAL", "text": "one"}, {"label_": "CARDINAL", "text": "two"}], "sentiment": 0.0}, {"text": "have in the second half of uh of 2023", "start": 1757.52, "duration": 5.759, "ents": [{"label_": "DATE", "text": "the second half"}, {"label_": "DATE", "text": "2023"}], "sentiment": -0.08333333333333333}, {"text": "uh to tag along and have first rights of", "start": 1785.12, "duration": 2.88, "ents": [{"label_": "ORDINAL", "text": "first"}], "sentiment": 0.25}, {"text": "one i think is actually better because", "start": 1792.96, "duration": 2.959, "ents": [], "sentiment": 0.5}, {"text": "market over two or three years after", "start": 1798.88, "duration": 4.399, "ents": [{"label_": "DATE", "text": "two or three years"}], "sentiment": 0.0}, {"text": "phase one the first five patients uh is", "start": 1814.799, "duration": 4.081, "ents": [{"label_": "CARDINAL", "text": "one"}, {"label_": "ORDINAL", "text": "first"}, {"label_": "CARDINAL", "text": "five"}], "sentiment": 0.25}, {"text": "the end of phase one", "start": 1817.279, "duration": 2.721, "ents": [{"label_": "CARDINAL", "text": "one"}], "sentiment": 0.0}, {"text": "at the end of phase one we'll be through", "start": 1820.0, "duration": 5.52, "ents": [], "sentiment": 0.0}, {"text": "phase two uh starts to get really", "start": 1853.6, "duration": 2.88, "ents": [{"label_": "CARDINAL", "text": "two"}], "sentiment": 0.2}, {"text": "four to five uh i'm sorry eight uh eight", "start": 1887.2, "duration": 3.44, "ents": [{"label_": "CARDINAL", "text": "four to five"}, {"label_": "CARDINAL", "text": "eight"}], "sentiment": -0.5}, {"text": "to five years", "start": 1889.2, "duration": 3.44, "ents": [{"label_": "DATE", "text": "five years"}], "sentiment": 0.0}, {"text": "uh we're an 810 million dollar company", "start": 1901.76, "duration": 4.799, "ents": [{"label_": "MONEY", "text": "810 million dollar"}], "sentiment": 0.0}, {"text": "now uh through phase one i'd like to", "start": 1904.24, "duration": 4.0, "ents": [], "sentiment": 0.0}, {"text": "210 million to 1.7 billion yep yep", "start": 1918.24, "duration": 6.08, "ents": [{"label_": "CARDINAL", "text": "210 million"}, {"label_": "CARDINAL", "text": "1.7 billion"}], "sentiment": 0.0}, {"text": "by five or six months uh", "start": 1942.96, "duration": 3.36, "ents": [{"label_": "DATE", "text": "five or six months"}], "sentiment": 0.0}, {"text": "more than that i think about seven", "start": 1945.279, "duration": 3.52, "ents": [{"label_": "CARDINAL", "text": "about seven"}], "sentiment": 0.5}, {"text": "lasts four to six weeks as opposed to uh", "start": 2046.399, "duration": 6.161, "ents": [{"label_": "DATE", "text": "four to six weeks"}], "sentiment": 0.0}, {"text": "four to six days no for 24 hours or 24", "start": 2048.879, "duration": 5.601, "ents": [{"label_": "DATE", "text": "four to six days"}, {"label_": "TIME", "text": "24 hours"}, {"label_": "DATE", "text": "24"}], "sentiment": 0.0}, {"text": "hours yeah that's right we're 21st so so", "start": 2052.56, "duration": 4.24, "ents": [], "sentiment": 0.14285714285714285}, {"text": "uh it was pretty simple formulation one", "start": 2057.76, "duration": 4.96, "ents": [{"label_": "CARDINAL", "text": "one"}], "sentiment": 0.125}, {"text": "plus one the components uh and you", "start": 2060.399, "duration": 3.361, "ents": [], "sentiment": 0.0}, {"text": "individually but you put three really", "start": 2063.76, "duration": 4.079, "ents": [{"label_": "CARDINAL", "text": "three"}], "sentiment": 0.1}, {"text": "one way or another if it's not us it's", "start": 2079.599, "duration": 2.48, "ents": [{"label_": "CARDINAL", "text": "one"}], "sentiment": 0.0}], "VIDEO_ID": "dtaAzRD0Tug", "VIDEO_DATA": [{"videoId": "dtaAzRD0Tug", "channelId": "UCxiA6FAQm7rPqb2Gl9pJ1-Q", "description": "Have you ever torn a: \u25cb muscle \u25cb rotator cuff \u25cb meniscus \u25cb cartilage How about someone you know? Or a favourite athlete?", "title": "Ortho Regenerative $ORTH Now In The Regulatory Lead For Technologies Addressing A $12B Market", "publishedAt": "2022-05-24T14:48:24Z"}]}